{
    "0":{
        "entity_id":2386,
        "entity_label":"<http:\/\/dbpedia.org\/resource\/Closer_(2004_film)>",
        "still_valid":false,
        "origin":"q(?w) :- musicComposer(?w,?y)",
        "score_calibrated":0.9999997616,
        "score_combined":0.9999997616,
        "local_kg_hit_rewriting":false,
        "online_kg_hit_rewriting":false,
        "local_kg_hit_original":false,
        "online_kg_hit_original":false
    },
    "1":{
        "entity_id":8794,
        "entity_label":"<http:\/\/dbpedia.org\/resource\/Portal:Nautical\/August\/02\/Selected_article>",
        "still_valid":false,
        "origin":"q(?w) :- musicComposer(?w,?y)",
        "score_calibrated":0.9999997616,
        "score_combined":0.9999997616,
        "local_kg_hit_rewriting":false,
        "online_kg_hit_rewriting":false,
        "local_kg_hit_original":false,
        "online_kg_hit_original":false
    },
    "2":{
        "entity_id":9969,
        "entity_label":"<http:\/\/dbpedia.org\/resource\/Selena_Gomez>",
        "still_valid":false,
        "origin":"q(?w) :- musicComposer(?w,?y)",
        "score_calibrated":0.9999996424,
        "score_combined":0.9999996424,
        "local_kg_hit_rewriting":false,
        "online_kg_hit_rewriting":false,
        "local_kg_hit_original":false,
        "online_kg_hit_original":false
    },
    "3":{
        "entity_id":8389,
        "entity_label":"<http:\/\/dbpedia.org\/resource\/Palm_Beach_County,_Florida>",
        "still_valid":false,
        "origin":"q(?w) :- musicComposer(?w,?y)",
        "score_calibrated":0.999999404,
        "score_combined":0.999999404,
        "local_kg_hit_rewriting":false,
        "online_kg_hit_rewriting":false,
        "local_kg_hit_original":false,
        "online_kg_hit_original":false
    },
    "4":{
        "entity_id":11790,
        "entity_label":"<http:\/\/dbpedia.org\/resource\/Tsui_Hark>",
        "still_valid":false,
        "origin":"q(?w) :- musicComposer(?w,?y)",
        "score_calibrated":0.9999992847,
        "score_combined":0.9999992847,
        "local_kg_hit_rewriting":false,
        "online_kg_hit_rewriting":false,
        "local_kg_hit_original":false,
        "online_kg_hit_original":false
    },
    "5":{
        "entity_id":7788,
        "entity_label":"<http:\/\/dbpedia.org\/resource\/NYPD_Blue>",
        "still_valid":false,
        "origin":"q(?w) :- musicComposer(?w,?y)",
        "score_calibrated":0.9999991655,
        "score_combined":0.9999991655,
        "local_kg_hit_rewriting":false,
        "online_kg_hit_rewriting":false,
        "local_kg_hit_original":false,
        "online_kg_hit_original":false
    },
    "6":{
        "entity_id":3674,
        "entity_label":"<http:\/\/dbpedia.org\/resource\/Eugene,_Oregon>",
        "still_valid":false,
        "origin":"q(?w) :- musicComposer(?w,?y)",
        "score_calibrated":0.9999988079,
        "score_combined":0.9999988079,
        "local_kg_hit_rewriting":false,
        "online_kg_hit_rewriting":false,
        "local_kg_hit_original":false,
        "online_kg_hit_original":false
    },
    "7":{
        "entity_id":11914,
        "entity_label":"<http:\/\/dbpedia.org\/resource\/United_States_Virgin_Islands>",
        "still_valid":false,
        "origin":"q(?w) :- musicComposer(?w,?y)",
        "score_calibrated":0.9999982119,
        "score_combined":0.9999982119,
        "local_kg_hit_rewriting":false,
        "online_kg_hit_rewriting":false,
        "local_kg_hit_original":false,
        "online_kg_hit_original":false
    },
    "8":{
        "entity_id":6811,
        "entity_label":"<http:\/\/dbpedia.org\/resource\/Ludhiana>",
        "still_valid":false,
        "origin":"q(?w) :- musicComposer(?w,?y)",
        "score_calibrated":0.9999978542,
        "score_combined":0.9999978542,
        "local_kg_hit_rewriting":false,
        "online_kg_hit_rewriting":false,
        "local_kg_hit_original":false,
        "online_kg_hit_original":false
    },
    "9":{
        "entity_id":6996,
        "entity_label":"<http:\/\/dbpedia.org\/resource\/Mangaka>",
        "still_valid":false,
        "origin":"q(?w) :- musicComposer(?w,?y)",
        "score_calibrated":0.9999976158,
        "score_combined":0.9999976158,
        "local_kg_hit_rewriting":false,
        "online_kg_hit_rewriting":false,
        "local_kg_hit_original":false,
        "online_kg_hit_original":false
    },
    "10":{
        "entity_id":8795,
        "entity_label":"<http:\/\/dbpedia.org\/resource\/Portal:Nautical\/January\/12\/Selected_article>",
        "still_valid":false,
        "origin":"q(?w) :- musicComposer(?w,?y)",
        "score_calibrated":0.9999973774,
        "score_combined":0.9999973774,
        "local_kg_hit_rewriting":false,
        "online_kg_hit_rewriting":false,
        "local_kg_hit_original":false,
        "online_kg_hit_original":false
    },
    "11":{
        "entity_id":1683,
        "entity_label":"<http:\/\/dbpedia.org\/resource\/Bruce_Dern>",
        "still_valid":false,
        "origin":"q(?w) :- musicComposer(?w,?y)",
        "score_calibrated":0.9999973774,
        "score_combined":0.9999973774,
        "local_kg_hit_rewriting":false,
        "online_kg_hit_rewriting":false,
        "local_kg_hit_original":false,
        "online_kg_hit_original":false
    },
    "12":{
        "entity_id":69,
        "entity_label":"<http:\/\/dbpedia.org\/resource\/21_Jump_Street_(film)>",
        "still_valid":false,
        "origin":"q(?w) :- musicComposer(?w,?y)",
        "score_calibrated":0.9999963045,
        "score_combined":0.9999963045,
        "local_kg_hit_rewriting":true,
        "online_kg_hit_rewriting":true,
        "local_kg_hit_original":true,
        "online_kg_hit_original":true
    },
    "13":{
        "entity_id":10297,
        "entity_label":"<http:\/\/dbpedia.org\/resource\/Sony>",
        "still_valid":false,
        "origin":"q(?w) :- musicComposer(?w,?y)",
        "score_calibrated":0.9999960661,
        "score_combined":0.9999960661,
        "local_kg_hit_rewriting":false,
        "online_kg_hit_rewriting":false,
        "local_kg_hit_original":false,
        "online_kg_hit_original":false
    },
    "14":{
        "entity_id":10298,
        "entity_label":"<http:\/\/dbpedia.org\/resource\/Sony_BMG>",
        "still_valid":false,
        "origin":"q(?w) :- musicComposer(?w,?y)",
        "score_calibrated":0.9999946356,
        "score_combined":0.9999946356,
        "local_kg_hit_rewriting":false,
        "online_kg_hit_rewriting":false,
        "local_kg_hit_original":false,
        "online_kg_hit_original":false
    },
    "15":{
        "entity_id":3685,
        "entity_label":"<http:\/\/dbpedia.org\/resource\/European_Americans>",
        "still_valid":false,
        "origin":"q(?w) :- musicComposer(?w,?y)",
        "score_calibrated":0.9999945164,
        "score_combined":0.9999945164,
        "local_kg_hit_rewriting":false,
        "online_kg_hit_rewriting":false,
        "local_kg_hit_original":false,
        "online_kg_hit_original":false
    },
    "16":{
        "entity_id":2198,
        "entity_label":"<http:\/\/dbpedia.org\/resource\/Chipping_Barnet>",
        "still_valid":false,
        "origin":"q(?w) :- musicComposer(?w,?y)",
        "score_calibrated":0.9999941587,
        "score_combined":0.9999941587,
        "local_kg_hit_rewriting":false,
        "online_kg_hit_rewriting":false,
        "local_kg_hit_original":false,
        "online_kg_hit_original":false
    },
    "17":{
        "entity_id":11431,
        "entity_label":"<http:\/\/dbpedia.org\/resource\/The_Warlords>",
        "still_valid":false,
        "origin":"q(?w) :- musicComposer(?w,?y)",
        "score_calibrated":0.9999941587,
        "score_combined":0.9999941587,
        "local_kg_hit_rewriting":true,
        "online_kg_hit_rewriting":true,
        "local_kg_hit_original":true,
        "online_kg_hit_original":true
    },
    "18":{
        "entity_id":2521,
        "entity_label":"<http:\/\/dbpedia.org\/resource\/Conservative_Party_(UK)>",
        "still_valid":false,
        "origin":"q(?w) :- musicComposer(?w,?y)",
        "score_calibrated":0.9999939203,
        "score_combined":0.9999939203,
        "local_kg_hit_rewriting":false,
        "online_kg_hit_rewriting":false,
        "local_kg_hit_original":false,
        "online_kg_hit_original":false
    },
    "19":{
        "entity_id":3179,
        "entity_label":"<http:\/\/dbpedia.org\/resource\/Dogville>",
        "still_valid":false,
        "origin":"q(?w) :- musicComposer(?w,?y)",
        "score_calibrated":0.9999939203,
        "score_combined":0.9999939203,
        "local_kg_hit_rewriting":false,
        "online_kg_hit_rewriting":false,
        "local_kg_hit_original":false,
        "online_kg_hit_original":false
    },
    "20":{
        "entity_id":3631,
        "entity_label":"<http:\/\/dbpedia.org\/resource\/Eric_Stoltz>",
        "still_valid":false,
        "origin":"q(?w) :- musicComposer(?w,?y)",
        "score_calibrated":0.9999935627,
        "score_combined":0.9999935627,
        "local_kg_hit_rewriting":false,
        "online_kg_hit_rewriting":false,
        "local_kg_hit_original":false,
        "online_kg_hit_original":false
    },
    "21":{
        "entity_id":2884,
        "entity_label":"<http:\/\/dbpedia.org\/resource\/David_H._DePatie>",
        "still_valid":false,
        "origin":"q(?w) :- musicComposer(?w,?y)",
        "score_calibrated":0.9999928474,
        "score_combined":0.9999928474,
        "local_kg_hit_rewriting":false,
        "online_kg_hit_rewriting":false,
        "local_kg_hit_original":false,
        "online_kg_hit_original":false
    },
    "22":{
        "entity_id":1684,
        "entity_label":"<http:\/\/dbpedia.org\/resource\/Bruce_Greenwood>",
        "still_valid":false,
        "origin":"q(?w) :- campus(?w,?x)",
        "score_calibrated":0.9999927282,
        "score_combined":0.9999927282,
        "local_kg_hit_rewriting":false,
        "online_kg_hit_rewriting":false,
        "local_kg_hit_original":false,
        "online_kg_hit_original":false
    },
    "23":{
        "entity_id":10967,
        "entity_label":"<http:\/\/dbpedia.org\/resource\/The_Assassination_of_Jesse_James_by_the_Coward_Robert_Ford>",
        "still_valid":false,
        "origin":"q(?w) :- musicComposer(?w,?y)",
        "score_calibrated":0.999992013,
        "score_combined":0.999992013,
        "local_kg_hit_rewriting":true,
        "online_kg_hit_rewriting":true,
        "local_kg_hit_original":true,
        "online_kg_hit_original":true
    },
    "24":{
        "entity_id":6196,
        "entity_label":"<http:\/\/dbpedia.org\/resource\/Kiernan_Shipka>",
        "still_valid":false,
        "origin":"q(?w) :- musicComposer(?w,?y)",
        "score_calibrated":0.9999918938,
        "score_combined":0.9999918938,
        "local_kg_hit_rewriting":false,
        "online_kg_hit_rewriting":false,
        "local_kg_hit_original":false,
        "online_kg_hit_original":false
    },
    "25":{
        "entity_id":10559,
        "entity_label":"<http:\/\/dbpedia.org\/resource\/Stepney>",
        "still_valid":false,
        "origin":"q(?w) :- musicComposer(?w,?y)",
        "score_calibrated":0.9999915361,
        "score_combined":0.9999915361,
        "local_kg_hit_rewriting":false,
        "online_kg_hit_rewriting":false,
        "local_kg_hit_original":false,
        "online_kg_hit_original":false
    },
    "26":{
        "entity_id":12618,
        "entity_label":"<http:\/\/dbpedia.org\/resource\/William_H._Macy>",
        "still_valid":false,
        "origin":"q(?w) :- musicComposer(?w,?y)",
        "score_calibrated":0.9999910593,
        "score_combined":0.9999910593,
        "local_kg_hit_rewriting":false,
        "online_kg_hit_rewriting":false,
        "local_kg_hit_original":false,
        "online_kg_hit_original":false
    },
    "27":{
        "entity_id":1624,
        "entity_label":"<http:\/\/dbpedia.org\/resource\/Bright_Star_(film)>",
        "still_valid":false,
        "origin":"q(?w) :- musicComposer(?w,?y)",
        "score_calibrated":0.9999907017,
        "score_combined":0.9999907017,
        "local_kg_hit_rewriting":false,
        "online_kg_hit_rewriting":true,
        "local_kg_hit_original":false,
        "online_kg_hit_original":true
    },
    "28":{
        "entity_id":11446,
        "entity_label":"<http:\/\/dbpedia.org\/resource\/The_Wire_(season_3)>",
        "still_valid":false,
        "origin":"q(?w) :- musicComposer(?w,?y)",
        "score_calibrated":0.999990344,
        "score_combined":0.999990344,
        "local_kg_hit_rewriting":false,
        "online_kg_hit_rewriting":false,
        "local_kg_hit_original":false,
        "online_kg_hit_original":false
    },
    "29":{
        "entity_id":3738,
        "entity_label":"<http:\/\/dbpedia.org\/resource\/FC_Bayern_Munich_II>",
        "still_valid":false,
        "origin":"q(?w) :- musicComposer(?w,?y)",
        "score_calibrated":0.9999901056,
        "score_combined":0.9999901056,
        "local_kg_hit_rewriting":false,
        "online_kg_hit_rewriting":false,
        "local_kg_hit_original":false,
        "online_kg_hit_original":false
    },
    "30":{
        "entity_id":8677,
        "entity_label":"<http:\/\/dbpedia.org\/resource\/Pierce_County,_Washington>",
        "still_valid":false,
        "origin":"q(?w) :- musicComposer(?w,?y)",
        "score_calibrated":0.9999899864,
        "score_combined":0.9999899864,
        "local_kg_hit_rewriting":false,
        "online_kg_hit_rewriting":false,
        "local_kg_hit_original":false,
        "online_kg_hit_original":false
    },
    "31":{
        "entity_id":88,
        "entity_label":"<http:\/\/dbpedia.org\/resource\/39th_Berlin_International_Film_Festival>",
        "still_valid":false,
        "origin":"q(?w) :- musicComposer(?w,?y)",
        "score_calibrated":0.9999893904,
        "score_combined":0.9999893904,
        "local_kg_hit_rewriting":false,
        "online_kg_hit_rewriting":false,
        "local_kg_hit_original":false,
        "online_kg_hit_original":false
    },
    "32":{
        "entity_id":8863,
        "entity_label":"<http:\/\/dbpedia.org\/resource\/Primetime_Emmy_Award_for_Outstanding_Drama_Series>",
        "still_valid":false,
        "origin":"q(?w) :- musicComposer(?w,?y)",
        "score_calibrated":0.9999878407,
        "score_combined":0.9999878407,
        "local_kg_hit_rewriting":false,
        "online_kg_hit_rewriting":false,
        "local_kg_hit_original":false,
        "online_kg_hit_original":false
    },
    "33":{
        "entity_id":12214,
        "entity_label":"<http:\/\/dbpedia.org\/resource\/Veneto>",
        "still_valid":false,
        "origin":"q(?w) :- musicComposer(?w,?y)",
        "score_calibrated":0.999987483,
        "score_combined":0.999987483,
        "local_kg_hit_rewriting":false,
        "online_kg_hit_rewriting":false,
        "local_kg_hit_original":false,
        "online_kg_hit_original":false
    },
    "34":{
        "entity_id":8707,
        "entity_label":"<http:\/\/dbpedia.org\/resource\/Pittsburgh_Steelers>",
        "still_valid":false,
        "origin":"q(?w) :- musicComposer(?w,?y)",
        "score_calibrated":0.9999873638,
        "score_combined":0.9999873638,
        "local_kg_hit_rewriting":false,
        "online_kg_hit_rewriting":false,
        "local_kg_hit_original":false,
        "online_kg_hit_original":false
    },
    "35":{
        "entity_id":4545,
        "entity_label":"<http:\/\/dbpedia.org\/resource\/Guelph>",
        "still_valid":false,
        "origin":"q(?w) :- musicComposer(?w,?y)",
        "score_calibrated":0.9999871254,
        "score_combined":0.9999871254,
        "local_kg_hit_rewriting":false,
        "online_kg_hit_rewriting":false,
        "local_kg_hit_original":false,
        "online_kg_hit_original":false
    },
    "36":{
        "entity_id":3951,
        "entity_label":"<http:\/\/dbpedia.org\/resource\/Forward_(association_football)>",
        "still_valid":false,
        "origin":"q(?w) :- musicComposer(?w,?y)",
        "score_calibrated":0.9999860525,
        "score_combined":0.9999860525,
        "local_kg_hit_rewriting":false,
        "online_kg_hit_rewriting":false,
        "local_kg_hit_original":false,
        "online_kg_hit_original":false
    },
    "37":{
        "entity_id":12461,
        "entity_label":"<http:\/\/dbpedia.org\/resource\/Water_(2005_film)>",
        "still_valid":false,
        "origin":"q(?w) :- musicComposer(?w,?y)",
        "score_calibrated":0.9999860525,
        "score_combined":0.9999860525,
        "local_kg_hit_rewriting":true,
        "online_kg_hit_rewriting":true,
        "local_kg_hit_original":true,
        "online_kg_hit_original":true
    },
    "38":{
        "entity_id":6742,
        "entity_label":"<http:\/\/dbpedia.org\/resource\/Lorraine_Bracco>",
        "still_valid":false,
        "origin":"q(?w) :- musicComposer(?w,?y)",
        "score_calibrated":0.9999856949,
        "score_combined":0.9999856949,
        "local_kg_hit_rewriting":false,
        "online_kg_hit_rewriting":false,
        "local_kg_hit_original":false,
        "online_kg_hit_original":false
    },
    "39":{
        "entity_id":11579,
        "entity_label":"<http:\/\/dbpedia.org\/resource\/Tisch_School_of_the_Arts>",
        "still_valid":false,
        "origin":"q(?w) :- musicComposer(?w,?y)",
        "score_calibrated":0.999984622,
        "score_combined":0.999984622,
        "local_kg_hit_rewriting":false,
        "online_kg_hit_rewriting":false,
        "local_kg_hit_original":false,
        "online_kg_hit_original":false
    },
    "40":{
        "entity_id":11445,
        "entity_label":"<http:\/\/dbpedia.org\/resource\/The_Wire_(season_2)>",
        "still_valid":false,
        "origin":"q(?w) :- musicComposer(?w,?y)",
        "score_calibrated":0.9999841452,
        "score_combined":0.9999841452,
        "local_kg_hit_rewriting":false,
        "online_kg_hit_rewriting":false,
        "local_kg_hit_original":false,
        "online_kg_hit_original":false
    },
    "41":{
        "entity_id":2922,
        "entity_label":"<http:\/\/dbpedia.org\/resource\/David_S._Goyer>",
        "still_valid":false,
        "origin":"q(?w) :- musicComposer(?w,?y)",
        "score_calibrated":0.999984026,
        "score_combined":0.999984026,
        "local_kg_hit_rewriting":false,
        "online_kg_hit_rewriting":false,
        "local_kg_hit_original":false,
        "online_kg_hit_original":false
    },
    "42":{
        "entity_id":605,
        "entity_label":"<http:\/\/dbpedia.org\/resource\/Amy_Nuttall>",
        "still_valid":false,
        "origin":"q(?w) :- musicComposer(?w,?y)",
        "score_calibrated":0.9999822378,
        "score_combined":0.9999822378,
        "local_kg_hit_rewriting":false,
        "online_kg_hit_rewriting":false,
        "local_kg_hit_original":false,
        "online_kg_hit_original":false
    },
    "43":{
        "entity_id":10055,
        "entity_label":"<http:\/\/dbpedia.org\/resource\/Shasta_County,_California>",
        "still_valid":false,
        "origin":"q(?w) :- musicComposer(?w,?y)",
        "score_calibrated":0.9999819994,
        "score_combined":0.9999819994,
        "local_kg_hit_rewriting":false,
        "online_kg_hit_rewriting":false,
        "local_kg_hit_original":false,
        "online_kg_hit_original":false
    },
    "44":{
        "entity_id":6457,
        "entity_label":"<http:\/\/dbpedia.org\/resource\/Lauren_Tom>",
        "still_valid":false,
        "origin":"q(?w) :- musicComposer(?w,?y)",
        "score_calibrated":0.9999818802,
        "score_combined":0.9999818802,
        "local_kg_hit_rewriting":false,
        "online_kg_hit_rewriting":false,
        "local_kg_hit_original":false,
        "online_kg_hit_original":false
    },
    "45":{
        "entity_id":5404,
        "entity_label":"<http:\/\/dbpedia.org\/resource\/James_K._Polk>",
        "still_valid":false,
        "origin":"q(?w) :- musicComposer(?w,?y)",
        "score_calibrated":0.9999815226,
        "score_combined":0.9999815226,
        "local_kg_hit_rewriting":false,
        "online_kg_hit_rewriting":false,
        "local_kg_hit_original":false,
        "online_kg_hit_original":false
    },
    "46":{
        "entity_id":2399,
        "entity_label":"<http:\/\/dbpedia.org\/resource\/Cobb_County,_Georgia>",
        "still_valid":false,
        "origin":"q(?w) :- musicComposer(?w,?y)",
        "score_calibrated":0.9999814034,
        "score_combined":0.9999814034,
        "local_kg_hit_rewriting":false,
        "online_kg_hit_rewriting":false,
        "local_kg_hit_original":false,
        "online_kg_hit_original":false
    },
    "47":{
        "entity_id":4988,
        "entity_label":"<http:\/\/dbpedia.org\/resource\/Howard_University>",
        "still_valid":false,
        "origin":"q(?w) :- musicComposer(?w,?y)",
        "score_calibrated":0.9999809265,
        "score_combined":0.9999809265,
        "local_kg_hit_rewriting":true,
        "online_kg_hit_rewriting":false,
        "local_kg_hit_original":true,
        "online_kg_hit_original":false
    },
    "48":{
        "entity_id":5004,
        "entity_label":"<http:\/\/dbpedia.org\/resource\/Hugh_Bonneville>",
        "still_valid":false,
        "origin":"q(?w) :- musicComposer(?w,?y)",
        "score_calibrated":0.9999792576,
        "score_combined":0.9999792576,
        "local_kg_hit_rewriting":false,
        "online_kg_hit_rewriting":false,
        "local_kg_hit_original":false,
        "online_kg_hit_original":false
    },
    "49":{
        "entity_id":9423,
        "entity_label":"<http:\/\/dbpedia.org\/resource\/Robert_Surtees_(cinematographer)>",
        "still_valid":false,
        "origin":"q(?w) :- musicComposer(?w,?y)",
        "score_calibrated":0.9999792576,
        "score_combined":0.9999792576,
        "local_kg_hit_rewriting":false,
        "online_kg_hit_rewriting":false,
        "local_kg_hit_original":false,
        "online_kg_hit_original":false
    },
    "50":{
        "entity_id":1141,
        "entity_label":"<http:\/\/dbpedia.org\/resource\/Bassoon>",
        "still_valid":false,
        "origin":"q(?w) :- musicComposer(?w,?y)",
        "score_calibrated":0.9999787807,
        "score_combined":0.9999787807,
        "local_kg_hit_rewriting":false,
        "online_kg_hit_rewriting":false,
        "local_kg_hit_original":false,
        "online_kg_hit_original":false
    },
    "51":{
        "entity_id":10516,
        "entity_label":"<http:\/\/dbpedia.org\/resource\/State_University_of_New_York_at_Purchase>",
        "still_valid":false,
        "origin":"q(?w) :- musicComposer(?w,?y)",
        "score_calibrated":0.9999785423,
        "score_combined":0.9999785423,
        "local_kg_hit_rewriting":false,
        "online_kg_hit_rewriting":false,
        "local_kg_hit_original":false,
        "online_kg_hit_original":false
    },
    "52":{
        "entity_id":8180,
        "entity_label":"<http:\/\/dbpedia.org\/resource\/Oahu>",
        "still_valid":false,
        "origin":"q(?w) :- musicComposer(?w,?y)",
        "score_calibrated":0.9999779463,
        "score_combined":0.9999779463,
        "local_kg_hit_rewriting":false,
        "online_kg_hit_rewriting":false,
        "local_kg_hit_original":false,
        "online_kg_hit_original":false
    },
    "53":{
        "entity_id":2162,
        "entity_label":"<http:\/\/dbpedia.org\/resource\/Chiapas>",
        "still_valid":false,
        "origin":"q(?w) :- musicComposer(?w,?y)",
        "score_calibrated":0.9999777079,
        "score_combined":0.9999777079,
        "local_kg_hit_rewriting":false,
        "online_kg_hit_rewriting":false,
        "local_kg_hit_original":false,
        "online_kg_hit_original":false
    },
    "54":{
        "entity_id":3231,
        "entity_label":"<http:\/\/dbpedia.org\/resource\/Doris_Roberts>",
        "still_valid":false,
        "origin":"q(?w) :- musicComposer(?w,?y)",
        "score_calibrated":0.9999763966,
        "score_combined":0.9999763966,
        "local_kg_hit_rewriting":false,
        "online_kg_hit_rewriting":false,
        "local_kg_hit_original":false,
        "online_kg_hit_original":false
    },
    "55":{
        "entity_id":4665,
        "entity_label":"<http:\/\/dbpedia.org\/resource\/Happy-Go-Lucky>",
        "still_valid":false,
        "origin":"q(?w) :- musicComposer(?w,?y)",
        "score_calibrated":0.9999762774,
        "score_combined":0.9999762774,
        "local_kg_hit_rewriting":false,
        "online_kg_hit_rewriting":false,
        "local_kg_hit_original":false,
        "online_kg_hit_original":false
    },
    "56":{
        "entity_id":1901,
        "entity_label":"<http:\/\/dbpedia.org\/resource\/Cardiac_arrest>",
        "still_valid":false,
        "origin":"q(?w) :- campus(?w,?x)",
        "score_calibrated":0.9999759197,
        "score_combined":0.9999759197,
        "local_kg_hit_rewriting":false,
        "online_kg_hit_rewriting":false,
        "local_kg_hit_original":false,
        "online_kg_hit_original":false
    },
    "57":{
        "entity_id":473,
        "entity_label":"<http:\/\/dbpedia.org\/resource\/Alice_in_Wonderland_(1985_film)>",
        "still_valid":false,
        "origin":"q(?w) :- musicComposer(?w,?y)",
        "score_calibrated":0.9999729395,
        "score_combined":0.9999729395,
        "local_kg_hit_rewriting":false,
        "online_kg_hit_rewriting":false,
        "local_kg_hit_original":false,
        "online_kg_hit_original":false
    },
    "58":{
        "entity_id":10851,
        "entity_label":"<http:\/\/dbpedia.org\/resource\/Taunton,_Massachusetts>",
        "still_valid":false,
        "origin":"q(?w) :- campus(?w,?x)",
        "score_calibrated":0.9999729395,
        "score_combined":0.9999729395,
        "local_kg_hit_rewriting":false,
        "online_kg_hit_rewriting":false,
        "local_kg_hit_original":false,
        "online_kg_hit_original":false
    },
    "59":{
        "entity_id":5248,
        "entity_label":"<http:\/\/dbpedia.org\/resource\/Irrfan_Khan>",
        "still_valid":false,
        "origin":"q(?w) :- musicComposer(?w,?y)",
        "score_calibrated":0.9999723434,
        "score_combined":0.9999723434,
        "local_kg_hit_rewriting":false,
        "online_kg_hit_rewriting":false,
        "local_kg_hit_original":false,
        "online_kg_hit_original":false
    },
    "60":{
        "entity_id":5616,
        "entity_label":"<http:\/\/dbpedia.org\/resource\/Jesse_Eisenberg>",
        "still_valid":false,
        "origin":"q(?w) :- musicComposer(?w,?y)",
        "score_calibrated":0.999972105,
        "score_combined":0.999972105,
        "local_kg_hit_rewriting":false,
        "online_kg_hit_rewriting":false,
        "local_kg_hit_original":false,
        "online_kg_hit_original":false
    },
    "61":{
        "entity_id":7617,
        "entity_label":"<http:\/\/dbpedia.org\/resource\/Mommie_Dearest_(film)>",
        "still_valid":false,
        "origin":"q(?w) :- musicComposer(?w,?y)",
        "score_calibrated":0.9999718666,
        "score_combined":0.9999718666,
        "local_kg_hit_rewriting":true,
        "online_kg_hit_rewriting":true,
        "local_kg_hit_original":true,
        "online_kg_hit_original":true
    },
    "62":{
        "entity_id":6894,
        "entity_label":"<http:\/\/dbpedia.org\/resource\/Machete_(film)>",
        "still_valid":false,
        "origin":"q(?w) :- musicComposer(?w,?y)",
        "score_calibrated":0.9999710321,
        "score_combined":0.9999710321,
        "local_kg_hit_rewriting":false,
        "online_kg_hit_rewriting":false,
        "local_kg_hit_original":false,
        "online_kg_hit_original":false
    },
    "63":{
        "entity_id":8705,
        "entity_label":"<http:\/\/dbpedia.org\/resource\/Pittsburgh>",
        "still_valid":false,
        "origin":"q(?w) :- musicComposer(?w,?y)",
        "score_calibrated":0.9999697208,
        "score_combined":0.9999697208,
        "local_kg_hit_rewriting":false,
        "online_kg_hit_rewriting":false,
        "local_kg_hit_original":false,
        "online_kg_hit_original":false
    },
    "64":{
        "entity_id":12686,
        "entity_label":"<http:\/\/dbpedia.org\/resource\/Wollongong>",
        "still_valid":false,
        "origin":"q(?w) :- musicComposer(?w,?y)",
        "score_calibrated":0.9999696016,
        "score_combined":0.9999696016,
        "local_kg_hit_rewriting":false,
        "online_kg_hit_rewriting":false,
        "local_kg_hit_original":false,
        "online_kg_hit_original":false
    },
    "65":{
        "entity_id":549,
        "entity_label":"<http:\/\/dbpedia.org\/resource\/Amblin_Entertainment>",
        "still_valid":false,
        "origin":"q(?w) :- musicComposer(?w,?y)",
        "score_calibrated":0.9999688864,
        "score_combined":0.9999688864,
        "local_kg_hit_rewriting":false,
        "online_kg_hit_rewriting":false,
        "local_kg_hit_original":false,
        "online_kg_hit_original":false
    },
    "66":{
        "entity_id":12702,
        "entity_label":"<http:\/\/dbpedia.org\/resource\/Woody_Harrelson>",
        "still_valid":false,
        "origin":"q(?w) :- musicComposer(?w,?y)",
        "score_calibrated":0.9999678135,
        "score_combined":0.9999678135,
        "local_kg_hit_rewriting":false,
        "online_kg_hit_rewriting":false,
        "local_kg_hit_original":false,
        "online_kg_hit_original":false
    },
    "67":{
        "entity_id":572,
        "entity_label":"<http:\/\/dbpedia.org\/resource\/American_Kennel_Club>",
        "still_valid":false,
        "origin":"q(?w) :- musicComposer(?w,?y)",
        "score_calibrated":0.9999673367,
        "score_combined":0.9999673367,
        "local_kg_hit_rewriting":false,
        "online_kg_hit_rewriting":false,
        "local_kg_hit_original":false,
        "online_kg_hit_original":false
    },
    "68":{
        "entity_id":702,
        "entity_label":"<http:\/\/dbpedia.org\/resource\/Ann_Curry>",
        "still_valid":false,
        "origin":"q(?w) :- musicComposer(?w,?y)",
        "score_calibrated":0.9999668598,
        "score_combined":0.9999668598,
        "local_kg_hit_rewriting":false,
        "online_kg_hit_rewriting":false,
        "local_kg_hit_original":false,
        "online_kg_hit_original":false
    },
    "69":{
        "entity_id":5271,
        "entity_label":"<http:\/\/dbpedia.org\/resource\/Israel_Defense_Forces>",
        "still_valid":false,
        "origin":"q(?w) :- musicComposer(?w,?y)",
        "score_calibrated":0.9999666214,
        "score_combined":0.9999666214,
        "local_kg_hit_rewriting":false,
        "online_kg_hit_rewriting":false,
        "local_kg_hit_original":false,
        "online_kg_hit_original":false
    },
    "70":{
        "entity_id":3615,
        "entity_label":"<http:\/\/dbpedia.org\/resource\/Epitaph_Records>",
        "still_valid":false,
        "origin":"q(?w) :- musicComposer(?w,?y)",
        "score_calibrated":0.9999660254,
        "score_combined":0.9999660254,
        "local_kg_hit_rewriting":false,
        "online_kg_hit_rewriting":false,
        "local_kg_hit_original":false,
        "online_kg_hit_original":false
    },
    "71":{
        "entity_id":2791,
        "entity_label":"<http:\/\/dbpedia.org\/resource\/Danny_Aiello>",
        "still_valid":false,
        "origin":"q(?w) :- musicComposer(?w,?y)",
        "score_calibrated":0.9999647141,
        "score_combined":0.9999647141,
        "local_kg_hit_rewriting":false,
        "online_kg_hit_rewriting":false,
        "local_kg_hit_original":false,
        "online_kg_hit_original":false
    },
    "72":{
        "entity_id":449,
        "entity_label":"<http:\/\/dbpedia.org\/resource\/Alexandre_Desplat>",
        "still_valid":false,
        "origin":"q(?w) :- musicComposer(?w,?y)",
        "score_calibrated":0.9999647141,
        "score_combined":0.9999647141,
        "local_kg_hit_rewriting":false,
        "online_kg_hit_rewriting":false,
        "local_kg_hit_original":false,
        "online_kg_hit_original":false
    },
    "73":{
        "entity_id":11957,
        "entity_label":"<http:\/\/dbpedia.org\/resource\/University_of_California,_Hastings_College_of_the_Law>",
        "still_valid":false,
        "origin":"q(?w) :- campus(?w,?x)",
        "score_calibrated":0.9999608994,
        "score_combined":0.9999608994,
        "local_kg_hit_rewriting":false,
        "online_kg_hit_rewriting":false,
        "local_kg_hit_original":false,
        "online_kg_hit_original":false
    },
    "74":{
        "entity_id":822,
        "entity_label":"<http:\/\/dbpedia.org\/resource\/Arminia_Bielefeld>",
        "still_valid":false,
        "origin":"q(?w) :- campus(?w,?x)",
        "score_calibrated":0.9999530315,
        "score_combined":0.9999530315,
        "local_kg_hit_rewriting":false,
        "online_kg_hit_rewriting":false,
        "local_kg_hit_original":false,
        "online_kg_hit_original":false
    },
    "75":{
        "entity_id":8837,
        "entity_label":"<http:\/\/dbpedia.org\/resource\/Precious_(film)>",
        "still_valid":false,
        "origin":"q(?w) :- campus(?w,?x)",
        "score_calibrated":0.9999412298,
        "score_combined":0.9999412298,
        "local_kg_hit_rewriting":false,
        "online_kg_hit_rewriting":false,
        "local_kg_hit_original":false,
        "online_kg_hit_original":false
    },
    "76":{
        "entity_id":9765,
        "entity_label":"<http:\/\/dbpedia.org\/resource\/San_Jose,_California>",
        "still_valid":false,
        "origin":"q(?w) :- campus(?w,?x)",
        "score_calibrated":0.9999388456,
        "score_combined":0.9999388456,
        "local_kg_hit_rewriting":false,
        "online_kg_hit_rewriting":false,
        "local_kg_hit_original":false,
        "online_kg_hit_original":false
    },
    "77":{
        "entity_id":1877,
        "entity_label":"<http:\/\/dbpedia.org\/resource\/Candlelight_Records>",
        "still_valid":false,
        "origin":"q(?w) :- campus(?w,?x)",
        "score_calibrated":0.9998867512,
        "score_combined":0.9998867512,
        "local_kg_hit_rewriting":false,
        "online_kg_hit_rewriting":false,
        "local_kg_hit_original":false,
        "online_kg_hit_original":false
    },
    "78":{
        "entity_id":5305,
        "entity_label":"<http:\/\/dbpedia.org\/resource\/J._T._Walsh>",
        "still_valid":false,
        "origin":"q(?w) :- campus(?w,?x)",
        "score_calibrated":0.9998803139,
        "score_combined":0.9998803139,
        "local_kg_hit_rewriting":false,
        "online_kg_hit_rewriting":false,
        "local_kg_hit_original":false,
        "online_kg_hit_original":false
    },
    "79":{
        "entity_id":12054,
        "entity_label":"<http:\/\/dbpedia.org\/resource\/University_of_Oslo>",
        "still_valid":false,
        "origin":"q(?w) :- campus(?w,?x)",
        "score_calibrated":0.99987638,
        "score_combined":0.99987638,
        "local_kg_hit_rewriting":false,
        "online_kg_hit_rewriting":false,
        "local_kg_hit_original":false,
        "online_kg_hit_original":false
    },
    "80":{
        "entity_id":8224,
        "entity_label":"<http:\/\/dbpedia.org\/resource\/Oklahoma!_(1955_film)>",
        "still_valid":false,
        "origin":"q(?w) :- campus(?w,?x)",
        "score_calibrated":0.9998691082,
        "score_combined":0.9998691082,
        "local_kg_hit_rewriting":true,
        "online_kg_hit_rewriting":false,
        "local_kg_hit_original":true,
        "online_kg_hit_original":true
    },
    "81":{
        "entity_id":2847,
        "entity_label":"<http:\/\/dbpedia.org\/resource\/Davenport,_Iowa>",
        "still_valid":false,
        "origin":"q(?w) :- campus(?w,?x)",
        "score_calibrated":0.999853611,
        "score_combined":0.999853611,
        "local_kg_hit_rewriting":false,
        "online_kg_hit_rewriting":false,
        "local_kg_hit_original":false,
        "online_kg_hit_original":false
    },
    "82":{
        "entity_id":7261,
        "entity_label":"<http:\/\/dbpedia.org\/resource\/Medford,_Oregon>",
        "still_valid":false,
        "origin":"q(?w) :- campus(?w,?x)",
        "score_calibrated":0.9998487234,
        "score_combined":0.9998487234,
        "local_kg_hit_rewriting":false,
        "online_kg_hit_rewriting":false,
        "local_kg_hit_original":false,
        "online_kg_hit_original":false
    },
    "83":{
        "entity_id":1528,
        "entity_label":"<http:\/\/dbpedia.org\/resource\/Boyz_II_Men>",
        "still_valid":false,
        "origin":"q(?w) :- campus(?w,?x)",
        "score_calibrated":0.9998447895,
        "score_combined":0.9998447895,
        "local_kg_hit_rewriting":false,
        "online_kg_hit_rewriting":false,
        "local_kg_hit_original":false,
        "online_kg_hit_original":false
    },
    "84":{
        "entity_id":12062,
        "entity_label":"<http:\/\/dbpedia.org\/resource\/University_of_Pisa>",
        "still_valid":false,
        "origin":"q(?w) :- campus(?w,?x)",
        "score_calibrated":0.9998283386,
        "score_combined":0.9998283386,
        "local_kg_hit_rewriting":true,
        "online_kg_hit_rewriting":true,
        "local_kg_hit_original":true,
        "online_kg_hit_original":true
    },
    "85":{
        "entity_id":11798,
        "entity_label":"<http:\/\/dbpedia.org\/resource\/Tulane_University_Law_School>",
        "still_valid":false,
        "origin":"q(?w) :- campus(?w,?x)",
        "score_calibrated":0.9998006225,
        "score_combined":0.9998006225,
        "local_kg_hit_rewriting":true,
        "online_kg_hit_rewriting":false,
        "local_kg_hit_original":true,
        "online_kg_hit_original":false
    },
    "86":{
        "entity_id":6619,
        "entity_label":"<http:\/\/dbpedia.org\/resource\/Lil_Wayne>",
        "still_valid":false,
        "origin":"q(?w) :- campus(?w,?x)",
        "score_calibrated":0.9997988343,
        "score_combined":0.9997988343,
        "local_kg_hit_rewriting":false,
        "online_kg_hit_rewriting":false,
        "local_kg_hit_original":false,
        "online_kg_hit_original":false
    },
    "87":{
        "entity_id":11963,
        "entity_label":"<http:\/\/dbpedia.org\/resource\/University_of_California,_Santa_Barbara>",
        "still_valid":false,
        "origin":"q(?w) :- campus(?w,?x)",
        "score_calibrated":0.9997785687,
        "score_combined":0.9997785687,
        "local_kg_hit_rewriting":true,
        "online_kg_hit_rewriting":false,
        "local_kg_hit_original":true,
        "online_kg_hit_original":false
    },
    "88":{
        "entity_id":11941,
        "entity_label":"<http:\/\/dbpedia.org\/resource\/University_of_Arizona>",
        "still_valid":false,
        "origin":"q(?w) :- campus(?w,?x)",
        "score_calibrated":0.9997757077,
        "score_combined":0.9997757077,
        "local_kg_hit_rewriting":false,
        "online_kg_hit_rewriting":false,
        "local_kg_hit_original":false,
        "online_kg_hit_original":false
    },
    "89":{
        "entity_id":1533,
        "entity_label":"<http:\/\/dbpedia.org\/resource\/Brad_Garrett>",
        "still_valid":false,
        "origin":"q(?w) :- campus(?w,?x)",
        "score_calibrated":0.9997395873,
        "score_combined":0.9997395873,
        "local_kg_hit_rewriting":false,
        "online_kg_hit_rewriting":false,
        "local_kg_hit_original":false,
        "online_kg_hit_original":false
    },
    "90":{
        "entity_id":11894,
        "entity_label":"<http:\/\/dbpedia.org\/resource\/United_States_Army>",
        "still_valid":false,
        "origin":"q(?w) :- campus(?w,?x)",
        "score_calibrated":0.9997336268,
        "score_combined":0.9997336268,
        "local_kg_hit_rewriting":false,
        "online_kg_hit_rewriting":false,
        "local_kg_hit_original":false,
        "online_kg_hit_original":false
    },
    "91":{
        "entity_id":4805,
        "entity_label":"<http:\/\/dbpedia.org\/resource\/Henan>",
        "still_valid":false,
        "origin":"q(?w) :- campus(?w,?x)",
        "score_calibrated":0.9997333884,
        "score_combined":0.9997333884,
        "local_kg_hit_rewriting":false,
        "online_kg_hit_rewriting":false,
        "local_kg_hit_original":false,
        "online_kg_hit_original":false
    },
    "92":{
        "entity_id":12081,
        "entity_label":"<http:\/\/dbpedia.org\/resource\/University_of_St_Andrews>",
        "still_valid":false,
        "origin":"q(?w) :- campus(?w,?x)",
        "score_calibrated":0.9997238517,
        "score_combined":0.9997238517,
        "local_kg_hit_rewriting":false,
        "online_kg_hit_rewriting":true,
        "local_kg_hit_original":false,
        "online_kg_hit_original":true
    },
    "93":{
        "entity_id":9693,
        "entity_label":"<http:\/\/dbpedia.org\/resource\/Saint_Petersburg_State_University>",
        "still_valid":false,
        "origin":"q(?w) :- campus(?w,?x)",
        "score_calibrated":0.9997205138,
        "score_combined":0.9997205138,
        "local_kg_hit_rewriting":true,
        "online_kg_hit_rewriting":true,
        "local_kg_hit_original":true,
        "online_kg_hit_original":true
    },
    "94":{
        "entity_id":9828,
        "entity_label":"<http:\/\/dbpedia.org\/resource\/Saratoga_County,_New_York>",
        "still_valid":false,
        "origin":"q(?w) :- campus(?w,?x)",
        "score_calibrated":0.9997088313,
        "score_combined":0.9997088313,
        "local_kg_hit_rewriting":false,
        "online_kg_hit_rewriting":false,
        "local_kg_hit_original":false,
        "online_kg_hit_original":false
    },
    "95":{
        "entity_id":12020,
        "entity_label":"<http:\/\/dbpedia.org\/resource\/University_of_Manitoba>",
        "still_valid":false,
        "origin":"q(?w) :- campus(?w,?x)",
        "score_calibrated":0.9996997118,
        "score_combined":0.9996997118,
        "local_kg_hit_rewriting":true,
        "online_kg_hit_rewriting":false,
        "local_kg_hit_original":true,
        "online_kg_hit_original":false
    },
    "96":{
        "entity_id":8676,
        "entity_label":"<http:\/\/dbpedia.org\/resource\/Pierce_Brosnan>",
        "still_valid":false,
        "origin":"q(?w) :- campus(?w,?x)",
        "score_calibrated":0.99967134,
        "score_combined":0.99967134,
        "local_kg_hit_rewriting":false,
        "online_kg_hit_rewriting":false,
        "local_kg_hit_original":false,
        "online_kg_hit_original":false
    },
    "97":{
        "entity_id":4719,
        "entity_label":"<http:\/\/dbpedia.org\/resource\/Harry_Turtledove>",
        "still_valid":false,
        "origin":"q(?w) :- campus(?w,?x)",
        "score_calibrated":0.9996634722,
        "score_combined":0.9996634722,
        "local_kg_hit_rewriting":false,
        "online_kg_hit_rewriting":false,
        "local_kg_hit_original":false,
        "online_kg_hit_original":false
    },
    "98":{
        "entity_id":1857,
        "entity_label":"<http:\/\/dbpedia.org\/resource\/Cameron_Mitchell_(actor)>",
        "still_valid":false,
        "origin":"q(?w) :- campus(?w,?x)",
        "score_calibrated":0.9996592999,
        "score_combined":0.9996592999,
        "local_kg_hit_rewriting":false,
        "online_kg_hit_rewriting":false,
        "local_kg_hit_original":false,
        "online_kg_hit_original":false
    },
    "99":{
        "entity_id":12497,
        "entity_label":"<http:\/\/dbpedia.org\/resource\/Wellington>",
        "still_valid":false,
        "origin":"q(?w) :- campus(?w,?x)",
        "score_calibrated":0.9996517897,
        "score_combined":0.9996517897,
        "local_kg_hit_rewriting":false,
        "online_kg_hit_rewriting":false,
        "local_kg_hit_original":false,
        "online_kg_hit_original":false
    },
    "100":{
        "entity_id":1843,
        "entity_label":"<http:\/\/dbpedia.org\/resource\/Camberwell>",
        "still_valid":false,
        "origin":"q(?w) :- campus(?w,?x)",
        "score_calibrated":0.9996517897,
        "score_combined":0.9996517897,
        "local_kg_hit_rewriting":false,
        "online_kg_hit_rewriting":false,
        "local_kg_hit_original":false,
        "online_kg_hit_original":false
    },
    "101":{
        "entity_id":9768,
        "entity_label":"<http:\/\/dbpedia.org\/resource\/San_Jose_State_University>",
        "still_valid":false,
        "origin":"q(?w) :- campus(?w,?x)",
        "score_calibrated":0.9996337891,
        "score_combined":0.9996337891,
        "local_kg_hit_rewriting":true,
        "online_kg_hit_rewriting":true,
        "local_kg_hit_original":true,
        "online_kg_hit_original":true
    },
    "102":{
        "entity_id":4280,
        "entity_label":"<http:\/\/dbpedia.org\/resource\/German_Army>",
        "still_valid":false,
        "origin":"q(?w) :- campus(?w,?x)",
        "score_calibrated":0.9996238947,
        "score_combined":0.9996238947,
        "local_kg_hit_rewriting":false,
        "online_kg_hit_rewriting":false,
        "local_kg_hit_original":false,
        "online_kg_hit_original":false
    },
    "103":{
        "entity_id":919,
        "entity_label":"<http:\/\/dbpedia.org\/resource\/Atlante_F.C.>",
        "still_valid":false,
        "origin":"q(?w) :- campus(?w,?x)",
        "score_calibrated":0.9996221066,
        "score_combined":0.9996221066,
        "local_kg_hit_rewriting":false,
        "online_kg_hit_rewriting":false,
        "local_kg_hit_original":false,
        "online_kg_hit_original":false
    },
    "104":{
        "entity_id":2230,
        "entity_label":"<http:\/\/dbpedia.org\/resource\/Chris_Parnell>",
        "still_valid":false,
        "origin":"q(?w) :- campus(?w,?x)",
        "score_calibrated":0.9996147156,
        "score_combined":0.9996147156,
        "local_kg_hit_rewriting":false,
        "online_kg_hit_rewriting":false,
        "local_kg_hit_original":false,
        "online_kg_hit_original":false
    },
    "105":{
        "entity_id":7583,
        "entity_label":"<http:\/\/dbpedia.org\/resource\/Mixed-sex_education>",
        "still_valid":false,
        "origin":"q(?w) :- campus(?w,?x)",
        "score_calibrated":0.9995748401,
        "score_combined":0.9995748401,
        "local_kg_hit_rewriting":false,
        "online_kg_hit_rewriting":false,
        "local_kg_hit_original":false,
        "online_kg_hit_original":false
    },
    "106":{
        "entity_id":1268,
        "entity_label":"<http:\/\/dbpedia.org\/resource\/Berlin-turkish.com>",
        "still_valid":false,
        "origin":"q(?w) :- campus(?w,?x)",
        "score_calibrated":0.9995701909,
        "score_combined":0.9995701909,
        "local_kg_hit_rewriting":false,
        "online_kg_hit_rewriting":false,
        "local_kg_hit_original":false,
        "online_kg_hit_original":false
    },
    "107":{
        "entity_id":12072,
        "entity_label":"<http:\/\/dbpedia.org\/resource\/University_of_Santo_Tomas>",
        "still_valid":false,
        "origin":"q(?w) :- campus(?w,?x)",
        "score_calibrated":0.9995606542,
        "score_combined":0.9995606542,
        "local_kg_hit_rewriting":true,
        "online_kg_hit_rewriting":false,
        "local_kg_hit_original":true,
        "online_kg_hit_original":false
    },
    "108":{
        "entity_id":239,
        "entity_label":"<http:\/\/dbpedia.org\/resource\/Academy_Award_for_Best_Production_Design>",
        "still_valid":false,
        "origin":"q(?w) :- campus(?w,?x)",
        "score_calibrated":0.9995592237,
        "score_combined":0.9995592237,
        "local_kg_hit_rewriting":false,
        "online_kg_hit_rewriting":false,
        "local_kg_hit_original":false,
        "online_kg_hit_original":false
    },
    "109":{
        "entity_id":4550,
        "entity_label":"<http:\/\/dbpedia.org\/resource\/Guildhall_School_of_Music_and_Drama>",
        "still_valid":false,
        "origin":"q(?w) :- campus(?w,?x)",
        "score_calibrated":0.9995427132,
        "score_combined":0.9995427132,
        "local_kg_hit_rewriting":false,
        "online_kg_hit_rewriting":false,
        "local_kg_hit_original":false,
        "online_kg_hit_original":false
    },
    "110":{
        "entity_id":11988,
        "entity_label":"<http:\/\/dbpedia.org\/resource\/University_of_Geneva>",
        "still_valid":false,
        "origin":"q(?w) :- campus(?w,?x)",
        "score_calibrated":0.9995342493,
        "score_combined":0.9995342493,
        "local_kg_hit_rewriting":true,
        "online_kg_hit_rewriting":false,
        "local_kg_hit_original":true,
        "online_kg_hit_original":false
    },
    "111":{
        "entity_id":9506,
        "entity_label":"<http:\/\/dbpedia.org\/resource\/Romantic_comedy_film>",
        "still_valid":false,
        "origin":"q(?w) :- campus(?w,?x)",
        "score_calibrated":0.9995305538,
        "score_combined":0.9995305538,
        "local_kg_hit_rewriting":false,
        "online_kg_hit_rewriting":false,
        "local_kg_hit_original":false,
        "online_kg_hit_original":false
    },
    "112":{
        "entity_id":9955,
        "entity_label":"<http:\/\/dbpedia.org\/resource\/Second_Punic_War>",
        "still_valid":false,
        "origin":"q(?w) :- campus(?w,?x)",
        "score_calibrated":0.9995163679,
        "score_combined":0.9995163679,
        "local_kg_hit_rewriting":false,
        "online_kg_hit_rewriting":false,
        "local_kg_hit_original":false,
        "online_kg_hit_original":false
    },
    "113":{
        "entity_id":2364,
        "entity_label":"<http:\/\/dbpedia.org\/resource\/Clergy>",
        "still_valid":false,
        "origin":"q(?w) :- campus(?w,?x)",
        "score_calibrated":0.9995113611,
        "score_combined":0.9995113611,
        "local_kg_hit_rewriting":false,
        "online_kg_hit_rewriting":false,
        "local_kg_hit_original":false,
        "online_kg_hit_original":false
    },
    "114":{
        "entity_id":9776,
        "entity_label":"<http:\/\/dbpedia.org\/resource\/San_Mateo_County,_California>",
        "still_valid":false,
        "origin":"q(?w) :- campus(?w,?x)",
        "score_calibrated":0.9995083809,
        "score_combined":0.9995083809,
        "local_kg_hit_rewriting":false,
        "online_kg_hit_rewriting":false,
        "local_kg_hit_original":false,
        "online_kg_hit_original":false
    },
    "115":{
        "entity_id":8204,
        "entity_label":"<http:\/\/dbpedia.org\/resource\/Odense>",
        "still_valid":false,
        "origin":"q(?w) :- campus(?w,?x)",
        "score_calibrated":0.999494195,
        "score_combined":0.999494195,
        "local_kg_hit_rewriting":false,
        "online_kg_hit_rewriting":false,
        "local_kg_hit_original":false,
        "online_kg_hit_original":false
    },
    "116":{
        "entity_id":12009,
        "entity_label":"<http:\/\/dbpedia.org\/resource\/University_of_Kiel>",
        "still_valid":false,
        "origin":"q(?w) :- campus(?w,?x)",
        "score_calibrated":0.9994897842,
        "score_combined":0.9994897842,
        "local_kg_hit_rewriting":true,
        "online_kg_hit_rewriting":false,
        "local_kg_hit_original":true,
        "online_kg_hit_original":false
    },
    "117":{
        "entity_id":4762,
        "entity_label":"<http:\/\/dbpedia.org\/resource\/Heart_(band)>",
        "still_valid":false,
        "origin":"q(?w) :- campus(?w,?x)",
        "score_calibrated":0.9994895458,
        "score_combined":0.9994895458,
        "local_kg_hit_rewriting":false,
        "online_kg_hit_rewriting":false,
        "local_kg_hit_original":false,
        "online_kg_hit_original":false
    },
    "118":{
        "entity_id":3640,
        "entity_label":"<http:\/\/dbpedia.org\/resource\/Eritrea>",
        "still_valid":false,
        "origin":"q(?w) :- campus(?w,?x)",
        "score_calibrated":0.9994871616,
        "score_combined":0.9994871616,
        "local_kg_hit_rewriting":false,
        "online_kg_hit_rewriting":false,
        "local_kg_hit_original":false,
        "online_kg_hit_original":false
    },
    "119":{
        "entity_id":5185,
        "entity_label":"<http:\/\/dbpedia.org\/resource\/Innocent_(actor)>",
        "still_valid":false,
        "origin":"q(?w) :- campus(?w,?x)",
        "score_calibrated":0.9994850159,
        "score_combined":0.9994850159,
        "local_kg_hit_rewriting":false,
        "online_kg_hit_rewriting":false,
        "local_kg_hit_original":false,
        "online_kg_hit_original":false
    },
    "120":{
        "entity_id":2803,
        "entity_label":"<http:\/\/dbpedia.org\/resource\/Dante_Ferretti>",
        "still_valid":false,
        "origin":"q(?w) :- campus(?w,?x)",
        "score_calibrated":0.9994781613,
        "score_combined":0.9994781613,
        "local_kg_hit_rewriting":false,
        "online_kg_hit_rewriting":false,
        "local_kg_hit_original":false,
        "online_kg_hit_original":false
    },
    "121":{
        "entity_id":12438,
        "entity_label":"<http:\/\/dbpedia.org\/resource\/Warwickshire>",
        "still_valid":false,
        "origin":"q(?w) :- campus(?w,?x)",
        "score_calibrated":0.9994766116,
        "score_combined":0.9994766116,
        "local_kg_hit_rewriting":false,
        "online_kg_hit_rewriting":false,
        "local_kg_hit_original":false,
        "online_kg_hit_original":false
    },
    "122":{
        "entity_id":5119,
        "entity_label":"<http:\/\/dbpedia.org\/resource\/Impressionism>",
        "still_valid":false,
        "origin":"q(?w) :- campus(?w,?x)",
        "score_calibrated":0.9994750619,
        "score_combined":0.9994750619,
        "local_kg_hit_rewriting":false,
        "online_kg_hit_rewriting":false,
        "local_kg_hit_original":false,
        "online_kg_hit_original":false
    },
    "123":{
        "entity_id":9729,
        "entity_label":"<http:\/\/dbpedia.org\/resource\/Sam_Wood>",
        "still_valid":false,
        "origin":"q(?w) :- campus(?w,?x)",
        "score_calibrated":0.9994443059,
        "score_combined":0.9994443059,
        "local_kg_hit_rewriting":false,
        "online_kg_hit_rewriting":false,
        "local_kg_hit_original":false,
        "online_kg_hit_original":false
    },
    "124":{
        "entity_id":11009,
        "entity_label":"<http:\/\/dbpedia.org\/resource\/The_Byrds>",
        "still_valid":false,
        "origin":"q(?w) :- campus(?w,?x)",
        "score_calibrated":0.9994336963,
        "score_combined":0.9994336963,
        "local_kg_hit_rewriting":false,
        "online_kg_hit_rewriting":false,
        "local_kg_hit_original":false,
        "online_kg_hit_original":false
    },
    "125":{
        "entity_id":1854,
        "entity_label":"<http:\/\/dbpedia.org\/resource\/Cameron_County,_Texas>",
        "still_valid":false,
        "origin":"q(?w) :- campus(?w,?x)",
        "score_calibrated":0.9994182587,
        "score_combined":0.9994182587,
        "local_kg_hit_rewriting":false,
        "online_kg_hit_rewriting":false,
        "local_kg_hit_original":false,
        "online_kg_hit_original":false
    },
    "126":{
        "entity_id":7827,
        "entity_label":"<http:\/\/dbpedia.org\/resource\/Nashville_Predators>",
        "still_valid":false,
        "origin":"q(?w) :- campus(?w,?x)",
        "score_calibrated":0.9994152784,
        "score_combined":0.9994152784,
        "local_kg_hit_rewriting":false,
        "online_kg_hit_rewriting":false,
        "local_kg_hit_original":false,
        "online_kg_hit_original":false
    },
    "127":{
        "entity_id":4284,
        "entity_label":"<http:\/\/dbpedia.org\/resource\/Germans>",
        "still_valid":false,
        "origin":"q(?w) :- campus(?w,?x)",
        "score_calibrated":0.9994120598,
        "score_combined":0.9994120598,
        "local_kg_hit_rewriting":false,
        "online_kg_hit_rewriting":false,
        "local_kg_hit_original":false,
        "online_kg_hit_original":false
    },
    "128":{
        "entity_id":8663,
        "entity_label":"<http:\/\/dbpedia.org\/resource\/Phoenix_Suns>",
        "still_valid":false,
        "origin":"q(?w) :- campus(?w,?x)",
        "score_calibrated":0.9994043112,
        "score_combined":0.9994043112,
        "local_kg_hit_rewriting":false,
        "online_kg_hit_rewriting":false,
        "local_kg_hit_original":false,
        "online_kg_hit_original":false
    },
    "129":{
        "entity_id":7170,
        "entity_label":"<http:\/\/dbpedia.org\/resource\/Mary_Tyler_Moore>",
        "still_valid":false,
        "origin":"q(?w) :- campus(?w,?x)",
        "score_calibrated":0.9994014502,
        "score_combined":0.9994014502,
        "local_kg_hit_rewriting":false,
        "online_kg_hit_rewriting":false,
        "local_kg_hit_original":false,
        "online_kg_hit_original":false
    },
    "130":{
        "entity_id":6512,
        "entity_label":"<http:\/\/dbpedia.org\/resource\/Legend_(1985_film)>",
        "still_valid":false,
        "origin":"q(?w) :- campus(?w,?x)",
        "score_calibrated":0.9993993044,
        "score_combined":0.9993993044,
        "local_kg_hit_rewriting":true,
        "online_kg_hit_rewriting":false,
        "local_kg_hit_original":true,
        "online_kg_hit_original":true
    },
    "131":{
        "entity_id":3676,
        "entity_label":"<http:\/\/dbpedia.org\/resource\/Eugene_O'Neill>",
        "still_valid":false,
        "origin":"q(?w) :- campus(?w,?x)",
        "score_calibrated":0.9993639588,
        "score_combined":0.9993639588,
        "local_kg_hit_rewriting":false,
        "online_kg_hit_rewriting":false,
        "local_kg_hit_original":false,
        "online_kg_hit_original":false
    },
    "132":{
        "entity_id":1847,
        "entity_label":"<http:\/\/dbpedia.org\/resource\/Cambridge,_Massachusetts>",
        "still_valid":false,
        "origin":"q(?w) :- campus(?w,?x)",
        "score_calibrated":0.9993633628,
        "score_combined":0.9993633628,
        "local_kg_hit_rewriting":false,
        "online_kg_hit_rewriting":false,
        "local_kg_hit_original":false,
        "online_kg_hit_original":false
    },
    "133":{
        "entity_id":6167,
        "entity_label":"<http:\/\/dbpedia.org\/resource\/Kevin_Corrigan>",
        "still_valid":false,
        "origin":"q(?w) :- campus(?w,?x)",
        "score_calibrated":0.9993599057,
        "score_combined":0.9993599057,
        "local_kg_hit_rewriting":false,
        "online_kg_hit_rewriting":false,
        "local_kg_hit_original":false,
        "online_kg_hit_original":false
    },
    "134":{
        "entity_id":4745,
        "entity_label":"<http:\/\/dbpedia.org\/resource\/Haverhill,_Massachusetts>",
        "still_valid":false,
        "origin":"q(?w) :- campus(?w,?x)",
        "score_calibrated":0.9993579984,
        "score_combined":0.9993579984,
        "local_kg_hit_rewriting":false,
        "online_kg_hit_rewriting":false,
        "local_kg_hit_original":false,
        "online_kg_hit_original":false
    },
    "135":{
        "entity_id":9695,
        "entity_label":"<http:\/\/dbpedia.org\/resource\/Saitama_Prefecture>",
        "still_valid":false,
        "origin":"q(?w) :- campus(?w,?x)",
        "score_calibrated":0.9993416667,
        "score_combined":0.9993416667,
        "local_kg_hit_rewriting":false,
        "online_kg_hit_rewriting":false,
        "local_kg_hit_original":false,
        "online_kg_hit_original":false
    },
    "136":{
        "entity_id":10653,
        "entity_label":"<http:\/\/dbpedia.org\/resource\/Submarine_(2010_film)>",
        "still_valid":false,
        "origin":"q(?w) :- campus(?w,?x)",
        "score_calibrated":0.9993336797,
        "score_combined":0.9993336797,
        "local_kg_hit_rewriting":false,
        "online_kg_hit_rewriting":false,
        "local_kg_hit_original":false,
        "online_kg_hit_original":false
    },
    "137":{
        "entity_id":12601,
        "entity_label":"<http:\/\/dbpedia.org\/resource\/Willem_II_(football_club)>",
        "still_valid":false,
        "origin":"q(?w) :- campus(?w,?x)",
        "score_calibrated":0.999333322,
        "score_combined":0.999333322,
        "local_kg_hit_rewriting":false,
        "online_kg_hit_rewriting":false,
        "local_kg_hit_original":false,
        "online_kg_hit_original":false
    },
    "138":{
        "entity_id":12236,
        "entity_label":"<http:\/\/dbpedia.org\/resource\/Vertigo_(film)>",
        "still_valid":false,
        "origin":"q(?w) :- campus(?w,?x)",
        "score_calibrated":0.999319911,
        "score_combined":0.999319911,
        "local_kg_hit_rewriting":true,
        "online_kg_hit_rewriting":false,
        "local_kg_hit_original":true,
        "online_kg_hit_original":true
    },
    "139":{
        "entity_id":2999,
        "entity_label":"<http:\/\/dbpedia.org\/resource\/Deathrock>",
        "still_valid":false,
        "origin":"q(?w) :- campus(?w,?x)",
        "score_calibrated":0.9993178844,
        "score_combined":0.9993178844,
        "local_kg_hit_rewriting":false,
        "online_kg_hit_rewriting":false,
        "local_kg_hit_original":false,
        "online_kg_hit_original":false
    },
    "140":{
        "entity_id":11796,
        "entity_label":"<http:\/\/dbpedia.org\/resource\/Tufts_University>",
        "still_valid":false,
        "origin":"q(?w) :- campus(?w,?x)",
        "score_calibrated":0.9993153811,
        "score_combined":0.9993153811,
        "local_kg_hit_rewriting":true,
        "online_kg_hit_rewriting":false,
        "local_kg_hit_original":true,
        "online_kg_hit_original":false
    },
    "141":{
        "entity_id":2201,
        "entity_label":"<http:\/\/dbpedia.org\/resource\/Chisago_County,_Minnesota>",
        "still_valid":false,
        "origin":"q(?w) :- campus(?w,?x)",
        "score_calibrated":0.9993078709,
        "score_combined":0.9993078709,
        "local_kg_hit_rewriting":false,
        "online_kg_hit_rewriting":false,
        "local_kg_hit_original":false,
        "online_kg_hit_original":false
    },
    "142":{
        "entity_id":12040,
        "entity_label":"<http:\/\/dbpedia.org\/resource\/University_of_New_Mexico>",
        "still_valid":false,
        "origin":"q(?w) :- campus(?w,?x)",
        "score_calibrated":0.9993035793,
        "score_combined":0.9993035793,
        "local_kg_hit_rewriting":true,
        "online_kg_hit_rewriting":true,
        "local_kg_hit_original":true,
        "online_kg_hit_original":true
    },
    "143":{
        "entity_id":1572,
        "entity_label":"<http:\/\/dbpedia.org\/resource\/Breakfast_on_Pluto_(film)>",
        "still_valid":false,
        "origin":"q(?w) :- campus(?w,?x)",
        "score_calibrated":0.9993020296,
        "score_combined":0.9993020296,
        "local_kg_hit_rewriting":false,
        "online_kg_hit_rewriting":false,
        "local_kg_hit_original":false,
        "online_kg_hit_original":false
    },
    "144":{
        "entity_id":7480,
        "entity_label":"<http:\/\/dbpedia.org\/resource\/Midland,_Texas>",
        "still_valid":false,
        "origin":"q(?w) :- campus(?w,?x)",
        "score_calibrated":0.9993004799,
        "score_combined":0.9993004799,
        "local_kg_hit_rewriting":false,
        "online_kg_hit_rewriting":false,
        "local_kg_hit_original":false,
        "online_kg_hit_original":false
    },
    "145":{
        "entity_id":4902,
        "entity_label":"<http:\/\/dbpedia.org\/resource\/Hold_Back_the_Dawn>",
        "still_valid":false,
        "origin":"q(?w) :- campus(?w,?x)",
        "score_calibrated":0.999293685,
        "score_combined":0.999293685,
        "local_kg_hit_rewriting":true,
        "online_kg_hit_rewriting":false,
        "local_kg_hit_original":true,
        "online_kg_hit_original":true
    },
    "146":{
        "entity_id":1542,
        "entity_label":"<http:\/\/dbpedia.org\/resource\/Bradley_Bell>",
        "still_valid":false,
        "origin":"q(?w) :- campus(?w,?x)",
        "score_calibrated":0.9992840886,
        "score_combined":0.9992840886,
        "local_kg_hit_rewriting":false,
        "online_kg_hit_rewriting":false,
        "local_kg_hit_original":false,
        "online_kg_hit_original":false
    },
    "147":{
        "entity_id":11974,
        "entity_label":"<http:\/\/dbpedia.org\/resource\/University_of_Copenhagen>",
        "still_valid":false,
        "origin":"q(?w) :- campus(?w,?x)",
        "score_calibrated":0.9992806315,
        "score_combined":0.9992806315,
        "local_kg_hit_rewriting":false,
        "online_kg_hit_rewriting":true,
        "local_kg_hit_original":false,
        "online_kg_hit_original":true
    },
    "148":{
        "entity_id":10486,
        "entity_label":"<http:\/\/dbpedia.org\/resource\/Star_Plus>",
        "still_valid":false,
        "origin":"q(?w) :- campus(?w,?x)",
        "score_calibrated":0.999263227,
        "score_combined":0.999263227,
        "local_kg_hit_rewriting":false,
        "online_kg_hit_rewriting":false,
        "local_kg_hit_original":false,
        "online_kg_hit_original":false
    },
    "149":{
        "entity_id":5168,
        "entity_label":"<http:\/\/dbpedia.org\/resource\/Indonesian_language>",
        "still_valid":false,
        "origin":"q(?w) :- campus(?w,?x)",
        "score_calibrated":0.9992540479,
        "score_combined":0.9992540479,
        "local_kg_hit_rewriting":false,
        "online_kg_hit_rewriting":false,
        "local_kg_hit_original":false,
        "online_kg_hit_original":false
    },
    "150":{
        "entity_id":959,
        "entity_label":"<http:\/\/dbpedia.org\/resource\/Australian_Broadcasting_Corporation>",
        "still_valid":false,
        "origin":"q(?w) :- campus(?w,?x)",
        "score_calibrated":0.999237299,
        "score_combined":0.999237299,
        "local_kg_hit_rewriting":false,
        "online_kg_hit_rewriting":false,
        "local_kg_hit_original":false,
        "online_kg_hit_original":false
    },
    "151":{
        "entity_id":5870,
        "entity_label":"<http:\/\/dbpedia.org\/resource\/Jon_Polito>",
        "still_valid":false,
        "origin":"q(?w) :- campus(?w,?x)",
        "score_calibrated":0.9992221594,
        "score_combined":0.9992221594,
        "local_kg_hit_rewriting":false,
        "online_kg_hit_rewriting":false,
        "local_kg_hit_original":false,
        "online_kg_hit_original":false
    },
    "152":{
        "entity_id":10444,
        "entity_label":"<http:\/\/dbpedia.org\/resource\/St._Petersburg,_Florida>",
        "still_valid":false,
        "origin":"q(?w) :- campus(?w,?x)",
        "score_calibrated":0.9992161989,
        "score_combined":0.9992161989,
        "local_kg_hit_rewriting":false,
        "online_kg_hit_rewriting":false,
        "local_kg_hit_original":false,
        "online_kg_hit_original":false
    },
    "153":{
        "entity_id":7971,
        "entity_label":"<http:\/\/dbpedia.org\/resource\/New_York_State_Senate>",
        "still_valid":false,
        "origin":"q(?w) :- campus(?w,?x)",
        "score_calibrated":0.9992146492,
        "score_combined":0.9992146492,
        "local_kg_hit_rewriting":false,
        "online_kg_hit_rewriting":false,
        "local_kg_hit_original":false,
        "online_kg_hit_original":false
    },
    "154":{
        "entity_id":8742,
        "entity_label":"<http:\/\/dbpedia.org\/resource\/Poitou-Charentes>",
        "still_valid":false,
        "origin":"q(?w) :- campus(?w,?x)",
        "score_calibrated":0.9992044568,
        "score_combined":0.9992044568,
        "local_kg_hit_rewriting":false,
        "online_kg_hit_rewriting":false,
        "local_kg_hit_original":false,
        "online_kg_hit_original":false
    },
    "155":{
        "entity_id":4744,
        "entity_label":"<http:\/\/dbpedia.org\/resource\/Haverford_College>",
        "still_valid":false,
        "origin":"q(?w) :- campus(?w,?x)",
        "score_calibrated":0.9991970658,
        "score_combined":0.9991970658,
        "local_kg_hit_rewriting":true,
        "online_kg_hit_rewriting":true,
        "local_kg_hit_original":true,
        "online_kg_hit_original":true
    },
    "156":{
        "entity_id":6661,
        "entity_label":"<http:\/\/dbpedia.org\/resource\/Lisp_(programming_language)>",
        "still_valid":false,
        "origin":"q(?w) :- campus(?w,?x)",
        "score_calibrated":0.9991849065,
        "score_combined":0.9991849065,
        "local_kg_hit_rewriting":false,
        "online_kg_hit_rewriting":false,
        "local_kg_hit_original":false,
        "online_kg_hit_original":false
    },
    "157":{
        "entity_id":8452,
        "entity_label":"<http:\/\/dbpedia.org\/resource\/Pat_Metheny_Group>",
        "still_valid":false,
        "origin":"q(?w) :- campus(?w,?x)",
        "score_calibrated":0.999181211,
        "score_combined":0.999181211,
        "local_kg_hit_rewriting":false,
        "online_kg_hit_rewriting":false,
        "local_kg_hit_original":false,
        "online_kg_hit_original":false
    },
    "158":{
        "entity_id":6876,
        "entity_label":"<http:\/\/dbpedia.org\/resource\/MTV_Video_Music_Award_for_Best_New_Artist>",
        "still_valid":false,
        "origin":"q(?w) :- campus(?w,?x)",
        "score_calibrated":0.9991782308,
        "score_combined":0.9991782308,
        "local_kg_hit_rewriting":false,
        "online_kg_hit_rewriting":false,
        "local_kg_hit_original":false,
        "online_kg_hit_original":false
    },
    "159":{
        "entity_id":12178,
        "entity_label":"<http:\/\/dbpedia.org\/resource\/Valparaiso_University>",
        "still_valid":false,
        "origin":"q(?w) :- campus(?w,?x)",
        "score_calibrated":0.9991614819,
        "score_combined":0.9991614819,
        "local_kg_hit_rewriting":true,
        "online_kg_hit_rewriting":false,
        "local_kg_hit_original":true,
        "online_kg_hit_original":false
    },
    "160":{
        "entity_id":1850,
        "entity_label":"<http:\/\/dbpedia.org\/resource\/Cambridgeshire>",
        "still_valid":false,
        "origin":"q(?w) :- campus(?w,?x)",
        "score_calibrated":0.9991544485,
        "score_combined":0.9991544485,
        "local_kg_hit_rewriting":false,
        "online_kg_hit_rewriting":false,
        "local_kg_hit_original":false,
        "online_kg_hit_original":false
    },
    "161":{
        "entity_id":3794,
        "entity_label":"<http:\/\/dbpedia.org\/resource\/Fantastic_Mr._Fox_(film)>",
        "still_valid":false,
        "origin":"q(?w) :- campus(?w,?x)",
        "score_calibrated":0.9991351962,
        "score_combined":0.9991351962,
        "local_kg_hit_rewriting":true,
        "online_kg_hit_rewriting":false,
        "local_kg_hit_original":true,
        "online_kg_hit_original":true
    },
    "162":{
        "entity_id":3352,
        "entity_label":"<http:\/\/dbpedia.org\/resource\/EA_Canada>",
        "still_valid":false,
        "origin":"q(?w) :- campus(?w,?x)",
        "score_calibrated":0.999130547,
        "score_combined":0.999130547,
        "local_kg_hit_rewriting":false,
        "online_kg_hit_rewriting":false,
        "local_kg_hit_original":false,
        "online_kg_hit_original":false
    },
    "163":{
        "entity_id":10301,
        "entity_label":"<http:\/\/dbpedia.org\/resource\/Sony_Pictures_Classics>",
        "still_valid":false,
        "origin":"q(?w) :- campus(?w,?x)",
        "score_calibrated":0.9991135001,
        "score_combined":0.9991135001,
        "local_kg_hit_rewriting":false,
        "online_kg_hit_rewriting":false,
        "local_kg_hit_original":false,
        "online_kg_hit_original":false
    },
    "164":{
        "entity_id":11036,
        "entity_label":"<http:\/\/dbpedia.org\/resource\/The_Constant_Gardener_(film)>",
        "still_valid":false,
        "origin":"q(?w) :- campus(?w,?x)",
        "score_calibrated":0.9991119504,
        "score_combined":0.9991119504,
        "local_kg_hit_rewriting":true,
        "online_kg_hit_rewriting":false,
        "local_kg_hit_original":true,
        "online_kg_hit_original":true
    },
    "165":{
        "entity_id":6911,
        "entity_label":"<http:\/\/dbpedia.org\/resource\/Madeline_Kahn>",
        "still_valid":false,
        "origin":"q(?w) :- campus(?w,?x)",
        "score_calibrated":0.9991115928,
        "score_combined":0.9991115928,
        "local_kg_hit_rewriting":false,
        "online_kg_hit_rewriting":false,
        "local_kg_hit_original":false,
        "online_kg_hit_original":false
    }
}