{
    "hits@3": {
        "local_kg_hit_rewriting": 0.6,
        "online_kg_hit_rewriting": 0.2,
        "local_kg_hit_original": 0.2533333333333333,
        "online_kg_hit_original": 0.36
    },
    "mrr": {
        "local_kg_hit_rewriting": 0.6853928272163565,
        "online_kg_hit_rewriting": 0.23064800094211865,
        "local_kg_hit_original": 0.4691364169599464,
        "online_kg_hit_original": 0.46671733783118974
    },
    "query_structure": "1p",
    "number_of_queries": 25,
    "model": {
        "selected_model_name": "TransE",
        "dim": 192,
        "epoch": 24
    },
    "dataset": "dbpedia15k",
    "cutoff_value": 100
}