{
    "hits@3": {
        "local_kg_hit_rewriting": 0.0,
        "online_kg_hit_rewriting": 0.0,
        "local_kg_hit_original": 0.0,
        "online_kg_hit_original": 0.0
    },
    "mrr": {
        "local_kg_hit_rewriting": 0.004,
        "online_kg_hit_rewriting": 0.001379310344827586,
        "local_kg_hit_original": 0.004,
        "online_kg_hit_original": 0.001379310344827586
    },
    "query_structure": "3p",
    "number_of_queries": 25,
    "model": {
        "selected_model_name": "BoxE",
        "dim": 192,
        "epoch": 24
    },
    "dataset": "dbpedia15k",
    "cutoff_value": 100
}