{
    "0":{
        "entity_id":56,
        "entity_label":"<https:\/\/www.wikidata.org\/wiki\/Q10061>",
        "still_valid":false,
        "origin":"q(?w) :- P22(?_,?x)^P25(?_,?x)^P40(?x,?w)",
        "score_calibrated":0.017227158,
        "score_combined":0.0002162361,
        "local_kg_hit_rewriting":false,
        "online_kg_hit_rewriting":false,
        "local_kg_hit_original":false,
        "online_kg_hit_original":false
    },
    "1":{
        "entity_id":133,
        "entity_label":"<https:\/\/www.wikidata.org\/wiki\/Q101384>",
        "still_valid":false,
        "origin":"q(?w) :- P22(?_,?x)^P25(?_,?x)^P40(?x,?w)",
        "score_calibrated":0.017227158,
        "score_combined":0.0002162361,
        "local_kg_hit_rewriting":false,
        "online_kg_hit_rewriting":false,
        "local_kg_hit_original":false,
        "online_kg_hit_original":false
    },
    "2":{
        "entity_id":121,
        "entity_label":"<https:\/\/www.wikidata.org\/wiki\/Q101172>",
        "still_valid":false,
        "origin":"q(?w) :- P22(?_,?x)^P25(?_,?x)^P40(?x,?w)",
        "score_calibrated":0.017227158,
        "score_combined":0.0002162361,
        "local_kg_hit_rewriting":false,
        "online_kg_hit_rewriting":false,
        "local_kg_hit_original":false,
        "online_kg_hit_original":false
    },
    "3":{
        "entity_id":31,
        "entity_label":"<https:\/\/www.wikidata.org\/wiki\/Q1002523>",
        "still_valid":false,
        "origin":"q(?w) :- P22(?_,?x)^P25(?_,?x)^P40(?x,?w)",
        "score_calibrated":0.017227158,
        "score_combined":0.0002162361,
        "local_kg_hit_rewriting":false,
        "online_kg_hit_rewriting":false,
        "local_kg_hit_original":false,
        "online_kg_hit_original":false
    },
    "4":{
        "entity_id":6,
        "entity_label":"<https:\/\/www.wikidata.org\/wiki\/Q1000874>",
        "still_valid":false,
        "origin":"q(?w) :- P22(?_,?x)^P25(?_,?x)^P40(?x,?w)",
        "score_calibrated":0.017227158,
        "score_combined":0.0002162361,
        "local_kg_hit_rewriting":false,
        "online_kg_hit_rewriting":false,
        "local_kg_hit_original":false,
        "online_kg_hit_original":false
    },
    "5":{
        "entity_id":4,
        "entity_label":"<https:\/\/www.wikidata.org\/wiki\/Q10007>",
        "still_valid":false,
        "origin":"q(?w) :- P22(?_,?x)^P25(?_,?x)^P40(?x,?w)",
        "score_calibrated":0.017227158,
        "score_combined":0.0002162361,
        "local_kg_hit_rewriting":false,
        "online_kg_hit_rewriting":false,
        "local_kg_hit_original":false,
        "online_kg_hit_original":false
    },
    "6":{
        "entity_id":17,
        "entity_label":"<https:\/\/www.wikidata.org\/wiki\/Q100175>",
        "still_valid":false,
        "origin":"q(?w) :- P22(?_,?x)^P25(?_,?x)^P40(?x,?w)",
        "score_calibrated":0.017227158,
        "score_combined":0.0002162361,
        "local_kg_hit_rewriting":false,
        "online_kg_hit_rewriting":false,
        "local_kg_hit_original":false,
        "online_kg_hit_original":false
    },
    "7":{
        "entity_id":127,
        "entity_label":"<https:\/\/www.wikidata.org\/wiki\/Q1012807>",
        "still_valid":false,
        "origin":"q(?w) :- P22(?_,?x)^P25(?_,?x)^P40(?x,?w)",
        "score_calibrated":0.017227158,
        "score_combined":0.0002162361,
        "local_kg_hit_rewriting":false,
        "online_kg_hit_rewriting":false,
        "local_kg_hit_original":false,
        "online_kg_hit_original":false
    },
    "8":{
        "entity_id":145,
        "entity_label":"<https:\/\/www.wikidata.org\/wiki\/Q101547>",
        "still_valid":false,
        "origin":"q(?w) :- P22(?_,?x)^P25(?_,?x)^P40(?x,?w)",
        "score_calibrated":0.017227158,
        "score_combined":0.0002162361,
        "local_kg_hit_rewriting":false,
        "online_kg_hit_rewriting":false,
        "local_kg_hit_original":false,
        "online_kg_hit_original":false
    },
    "9":{
        "entity_id":32,
        "entity_label":"<https:\/\/www.wikidata.org\/wiki\/Q1002546>",
        "still_valid":false,
        "origin":"q(?w) :- P22(?_,?x)^P25(?_,?x)^P40(?x,?w)",
        "score_calibrated":0.017227158,
        "score_combined":0.0002162361,
        "local_kg_hit_rewriting":false,
        "online_kg_hit_rewriting":false,
        "local_kg_hit_original":false,
        "online_kg_hit_original":false
    },
    "10":{
        "entity_id":113,
        "entity_label":"<https:\/\/www.wikidata.org\/wiki\/Q1010767>",
        "still_valid":false,
        "origin":"q(?w) :- P22(?_,?x)^P25(?_,?x)^P40(?x,?w)",
        "score_calibrated":0.017227158,
        "score_combined":0.0002162361,
        "local_kg_hit_rewriting":false,
        "online_kg_hit_rewriting":false,
        "local_kg_hit_original":false,
        "online_kg_hit_original":false
    },
    "11":{
        "entity_id":181,
        "entity_label":"<https:\/\/www.wikidata.org\/wiki\/Q1018548>",
        "still_valid":false,
        "origin":"q(?w) :- P22(?_,?x)^P25(?_,?x)^P40(?x,?w)",
        "score_calibrated":0.017227158,
        "score_combined":0.0002162361,
        "local_kg_hit_rewriting":false,
        "online_kg_hit_rewriting":false,
        "local_kg_hit_original":false,
        "online_kg_hit_original":false
    },
    "12":{
        "entity_id":149,
        "entity_label":"<https:\/\/www.wikidata.org\/wiki\/Q101581>",
        "still_valid":false,
        "origin":"q(?w) :- P22(?_,?x)^P25(?_,?x)^P40(?x,?w)",
        "score_calibrated":0.017227158,
        "score_combined":0.0002162361,
        "local_kg_hit_rewriting":false,
        "online_kg_hit_rewriting":false,
        "local_kg_hit_original":false,
        "online_kg_hit_original":false
    },
    "13":{
        "entity_id":58,
        "entity_label":"<https:\/\/www.wikidata.org\/wiki\/Q1006265>",
        "still_valid":false,
        "origin":"q(?w) :- P22(?_,?x)^P25(?_,?x)^P40(?x,?w)",
        "score_calibrated":0.017227158,
        "score_combined":0.0002162361,
        "local_kg_hit_rewriting":false,
        "online_kg_hit_rewriting":false,
        "local_kg_hit_original":false,
        "online_kg_hit_original":false
    },
    "14":{
        "entity_id":7764,
        "entity_label":"<https:\/\/www.wikidata.org\/wiki\/Q133147>",
        "still_valid":false,
        "origin":"q(?w) :- P22(?_,?x)^P25(?_,?x)^P40(?x,?w)",
        "score_calibrated":0.0000277128,
        "score_combined":0.0000003479,
        "local_kg_hit_rewriting":false,
        "online_kg_hit_rewriting":false,
        "local_kg_hit_original":false,
        "online_kg_hit_original":false
    },
    "15":{
        "entity_id":31193,
        "entity_label":"<https:\/\/www.wikidata.org\/wiki\/Q232761>",
        "still_valid":false,
        "origin":"q(?w) :- P22(?_,?x)^P25(?_,?x)^P40(?x,?w)",
        "score_calibrated":0.0000262503,
        "score_combined":0.0000003295,
        "local_kg_hit_rewriting":false,
        "online_kg_hit_rewriting":false,
        "local_kg_hit_original":false,
        "online_kg_hit_original":false
    },
    "16":{
        "entity_id":60,
        "entity_label":"<https:\/\/www.wikidata.org\/wiki\/Q10065>",
        "still_valid":false,
        "origin":"q(?w) :- P22(?_,?x)^P25(?_,?x)^P40(?x,?w)",
        "score_calibrated":0.0000247469,
        "score_combined":0.0000003106,
        "local_kg_hit_rewriting":false,
        "online_kg_hit_rewriting":false,
        "local_kg_hit_original":false,
        "online_kg_hit_original":false
    },
    "17":{
        "entity_id":43407,
        "entity_label":"<https:\/\/www.wikidata.org\/wiki\/Q2994836>",
        "still_valid":false,
        "origin":"q(?w) :- P22(?_,?x)^P25(?_,?x)^P40(?x,?w)",
        "score_calibrated":0.00002076,
        "score_combined":0.0000002606,
        "local_kg_hit_rewriting":false,
        "online_kg_hit_rewriting":false,
        "local_kg_hit_original":false,
        "online_kg_hit_original":false
    },
    "18":{
        "entity_id":66411,
        "entity_label":"<https:\/\/www.wikidata.org\/wiki\/Q4726013>",
        "still_valid":false,
        "origin":"q(?w) :- P22(?_,?x)^P25(?_,?x)^P40(?x,?w)",
        "score_calibrated":0.0000196202,
        "score_combined":0.0000002463,
        "local_kg_hit_rewriting":false,
        "online_kg_hit_rewriting":false,
        "local_kg_hit_original":false,
        "online_kg_hit_original":false
    },
    "19":{
        "entity_id":56174,
        "entity_label":"<https:\/\/www.wikidata.org\/wiki\/Q3756712>",
        "still_valid":false,
        "origin":"q(?w) :- P22(?_,?x)^P25(?_,?x)^P40(?x,?w)",
        "score_calibrated":0.0000190029,
        "score_combined":0.0000002385,
        "local_kg_hit_rewriting":false,
        "online_kg_hit_rewriting":false,
        "local_kg_hit_original":false,
        "online_kg_hit_original":false
    },
    "20":{
        "entity_id":68526,
        "entity_label":"<https:\/\/www.wikidata.org\/wiki\/Q4844452>",
        "still_valid":false,
        "origin":"q(?w) :- P22(?_,?x)^P25(?_,?x)^P40(?x,?w)",
        "score_calibrated":0.0000163923,
        "score_combined":0.0000002058,
        "local_kg_hit_rewriting":false,
        "online_kg_hit_rewriting":false,
        "local_kg_hit_original":false,
        "online_kg_hit_original":false
    },
    "21":{
        "entity_id":110663,
        "entity_label":"<https:\/\/www.wikidata.org\/wiki\/Q8250818>",
        "still_valid":false,
        "origin":"q(?w) :- P22(?_,?x)^P25(?_,?x)^P40(?x,?w)",
        "score_calibrated":0.0000162407,
        "score_combined":0.0000002039,
        "local_kg_hit_rewriting":false,
        "online_kg_hit_rewriting":false,
        "local_kg_hit_original":false,
        "online_kg_hit_original":false
    },
    "22":{
        "entity_id":58116,
        "entity_label":"<https:\/\/www.wikidata.org\/wiki\/Q3990167>",
        "still_valid":false,
        "origin":"q(?w) :- P22(?_,?x)^P25(?_,?x)^P40(?x,?w)",
        "score_calibrated":0.0000138306,
        "score_combined":0.0000001736,
        "local_kg_hit_rewriting":false,
        "online_kg_hit_rewriting":false,
        "local_kg_hit_original":false,
        "online_kg_hit_original":false
    },
    "23":{
        "entity_id":68525,
        "entity_label":"<https:\/\/www.wikidata.org\/wiki\/Q4844450>",
        "still_valid":false,
        "origin":"q(?w) :- P22(?_,?x)^P25(?_,?x)^P40(?x,?w)",
        "score_calibrated":0.0000135053,
        "score_combined":0.0000001695,
        "local_kg_hit_rewriting":false,
        "online_kg_hit_rewriting":false,
        "local_kg_hit_original":false,
        "online_kg_hit_original":false
    },
    "24":{
        "entity_id":2027,
        "entity_label":"<https:\/\/www.wikidata.org\/wiki\/Q10931661>",
        "still_valid":false,
        "origin":"q(?w) :- P22(?_,?x)^P25(?_,?x)^P40(?x,?w)",
        "score_calibrated":0.0000134969,
        "score_combined":0.0000001694,
        "local_kg_hit_rewriting":false,
        "online_kg_hit_rewriting":false,
        "local_kg_hit_original":false,
        "online_kg_hit_original":false
    },
    "25":{
        "entity_id":23737,
        "entity_label":"<https:\/\/www.wikidata.org\/wiki\/Q1942360>",
        "still_valid":false,
        "origin":"q(?w) :- P22(?_,?x)^P25(?_,?x)^P40(?x,?w)",
        "score_calibrated":0.0000123678,
        "score_combined":0.0000001552,
        "local_kg_hit_rewriting":false,
        "online_kg_hit_rewriting":false,
        "local_kg_hit_original":false,
        "online_kg_hit_original":false
    },
    "26":{
        "entity_id":54637,
        "entity_label":"<https:\/\/www.wikidata.org\/wiki\/Q362113>",
        "still_valid":false,
        "origin":"q(?w) :- P22(?_,?x)^P25(?_,?x)^P40(?x,?w)",
        "score_calibrated":0.0000118295,
        "score_combined":0.0000001485,
        "local_kg_hit_rewriting":false,
        "online_kg_hit_rewriting":false,
        "local_kg_hit_original":false,
        "online_kg_hit_original":false
    },
    "27":{
        "entity_id":70209,
        "entity_label":"<https:\/\/www.wikidata.org\/wiki\/Q4963108>",
        "still_valid":false,
        "origin":"q(?w) :- P22(?_,?x)^P25(?_,?x)^P40(?x,?w)",
        "score_calibrated":0.0000115196,
        "score_combined":0.0000001446,
        "local_kg_hit_rewriting":false,
        "online_kg_hit_rewriting":false,
        "local_kg_hit_original":false,
        "online_kg_hit_original":false
    },
    "28":{
        "entity_id":37050,
        "entity_label":"<https:\/\/www.wikidata.org\/wiki\/Q263368>",
        "still_valid":false,
        "origin":"q(?w) :- P22(?_,?x)^P25(?_,?x)^P40(?x,?w)",
        "score_calibrated":0.0000099618,
        "score_combined":0.000000125,
        "local_kg_hit_rewriting":false,
        "online_kg_hit_rewriting":false,
        "local_kg_hit_original":false,
        "online_kg_hit_original":false
    },
    "29":{
        "entity_id":27901,
        "entity_label":"<https:\/\/www.wikidata.org\/wiki\/Q2120325>",
        "still_valid":false,
        "origin":"q(?w) :- P22(?_,?x)^P25(?_,?x)^P40(?x,?w)",
        "score_calibrated":0.0000095822,
        "score_combined":0.0000001203,
        "local_kg_hit_rewriting":false,
        "online_kg_hit_rewriting":false,
        "local_kg_hit_original":false,
        "online_kg_hit_original":false
    },
    "30":{
        "entity_id":79962,
        "entity_label":"<https:\/\/www.wikidata.org\/wiki\/Q553897>",
        "still_valid":false,
        "origin":"q(?w) :- P22(?_,?x)^P25(?_,?x)^P40(?x,?w)",
        "score_calibrated":0.0000090711,
        "score_combined":0.0000001139,
        "local_kg_hit_rewriting":false,
        "online_kg_hit_rewriting":false,
        "local_kg_hit_original":false,
        "online_kg_hit_original":false
    },
    "31":{
        "entity_id":64315,
        "entity_label":"<https:\/\/www.wikidata.org\/wiki\/Q462997>",
        "still_valid":false,
        "origin":"q(?w) :- P22(?_,?x)^P25(?_,?x)^P40(?x,?w)",
        "score_calibrated":0.0000080384,
        "score_combined":0.0000001009,
        "local_kg_hit_rewriting":false,
        "online_kg_hit_rewriting":false,
        "local_kg_hit_original":false,
        "online_kg_hit_original":false
    },
    "32":{
        "entity_id":2357,
        "entity_label":"<https:\/\/www.wikidata.org\/wiki\/Q11093947>",
        "still_valid":false,
        "origin":"q(?w) :- P22(?_,?x)^P25(?_,?x)^P40(?x,?w)",
        "score_calibrated":0.0000065822,
        "score_combined":0.0000000826,
        "local_kg_hit_rewriting":false,
        "online_kg_hit_rewriting":false,
        "local_kg_hit_original":false,
        "online_kg_hit_original":false
    },
    "33":{
        "entity_id":63191,
        "entity_label":"<https:\/\/www.wikidata.org\/wiki\/Q45465>",
        "still_valid":false,
        "origin":"q(?w) :- P22(?_,?x)^P25(?_,?x)^P40(?x,?w)",
        "score_calibrated":0.0000064771,
        "score_combined":0.0000000813,
        "local_kg_hit_rewriting":false,
        "online_kg_hit_rewriting":false,
        "local_kg_hit_original":false,
        "online_kg_hit_original":false
    },
    "34":{
        "entity_id":97783,
        "entity_label":"<https:\/\/www.wikidata.org\/wiki\/Q71086>",
        "still_valid":false,
        "origin":"q(?w) :- P22(?_,?x)^P25(?_,?x)^P40(?x,?w)",
        "score_calibrated":0.000006077,
        "score_combined":0.0000000763,
        "local_kg_hit_rewriting":false,
        "online_kg_hit_rewriting":false,
        "local_kg_hit_original":false,
        "online_kg_hit_original":false
    },
    "35":{
        "entity_id":55567,
        "entity_label":"<https:\/\/www.wikidata.org\/wiki\/Q370649>",
        "still_valid":false,
        "origin":"q(?w) :- P22(?_,?x)^P25(?_,?x)^P40(?x,?w)",
        "score_calibrated":0.0000058585,
        "score_combined":0.0000000735,
        "local_kg_hit_rewriting":false,
        "online_kg_hit_rewriting":false,
        "local_kg_hit_original":false,
        "online_kg_hit_original":false
    },
    "36":{
        "entity_id":2434,
        "entity_label":"<https:\/\/www.wikidata.org\/wiki\/Q11120493>",
        "still_valid":false,
        "origin":"q(?w) :- P22(?_,?x)^P25(?_,?x)^P40(?x,?w)",
        "score_calibrated":0.0000057685,
        "score_combined":0.0000000724,
        "local_kg_hit_rewriting":false,
        "online_kg_hit_rewriting":false,
        "local_kg_hit_original":false,
        "online_kg_hit_original":false
    },
    "37":{
        "entity_id":49841,
        "entity_label":"<https:\/\/www.wikidata.org\/wiki\/Q332632>",
        "still_valid":false,
        "origin":"q(?w) :- P22(?_,?x)^P25(?_,?x)^P40(?x,?w)",
        "score_calibrated":0.0000057147,
        "score_combined":0.0000000717,
        "local_kg_hit_rewriting":false,
        "online_kg_hit_rewriting":false,
        "local_kg_hit_original":false,
        "online_kg_hit_original":false
    },
    "38":{
        "entity_id":52731,
        "entity_label":"<https:\/\/www.wikidata.org\/wiki\/Q3498141>",
        "still_valid":false,
        "origin":"q(?w) :- P22(?_,?x)^P25(?_,?x)^P40(?x,?w)",
        "score_calibrated":0.0000054224,
        "score_combined":0.0000000681,
        "local_kg_hit_rewriting":false,
        "online_kg_hit_rewriting":false,
        "local_kg_hit_original":false,
        "online_kg_hit_original":false
    },
    "39":{
        "entity_id":89933,
        "entity_label":"<https:\/\/www.wikidata.org\/wiki\/Q63775>",
        "still_valid":false,
        "origin":"q(?w) :- P22(?_,?x)^P25(?_,?x)^P40(?x,?w)",
        "score_calibrated":0.0000045385,
        "score_combined":0.000000057,
        "local_kg_hit_rewriting":false,
        "online_kg_hit_rewriting":false,
        "local_kg_hit_original":false,
        "online_kg_hit_original":false
    },
    "40":{
        "entity_id":48419,
        "entity_label":"<https:\/\/www.wikidata.org\/wiki\/Q325092>",
        "still_valid":false,
        "origin":"q(?w) :- P22(?_,?x)^P25(?_,?x)^P40(?x,?w)",
        "score_calibrated":0.0000044859,
        "score_combined":0.0000000563,
        "local_kg_hit_rewriting":false,
        "online_kg_hit_rewriting":false,
        "local_kg_hit_original":false,
        "online_kg_hit_original":false
    },
    "41":{
        "entity_id":7669,
        "entity_label":"<https:\/\/www.wikidata.org\/wiki\/Q1325720>",
        "still_valid":false,
        "origin":"q(?w) :- P22(?_,?x)^P25(?_,?x)^P40(?x,?w)",
        "score_calibrated":0.0000043078,
        "score_combined":0.0000000541,
        "local_kg_hit_rewriting":false,
        "online_kg_hit_rewriting":false,
        "local_kg_hit_original":false,
        "online_kg_hit_original":false
    },
    "42":{
        "entity_id":1091,
        "entity_label":"<https:\/\/www.wikidata.org\/wiki\/Q1058346>",
        "still_valid":false,
        "origin":"q(?w) :- P22(?_,?x)^P25(?_,?x)^P40(?x,?w)",
        "score_calibrated":0.0000042789,
        "score_combined":0.0000000537,
        "local_kg_hit_rewriting":false,
        "online_kg_hit_rewriting":false,
        "local_kg_hit_original":false,
        "online_kg_hit_original":false
    },
    "43":{
        "entity_id":53,
        "entity_label":"<https:\/\/www.wikidata.org\/wiki\/Q10059>",
        "still_valid":false,
        "origin":"q(?w) :- P22(?_,?x)^P25(?_,?x)^P40(?x,?w)",
        "score_calibrated":0.0000042332,
        "score_combined":0.0000000531,
        "local_kg_hit_rewriting":false,
        "online_kg_hit_rewriting":false,
        "local_kg_hit_original":false,
        "online_kg_hit_original":false
    },
    "44":{
        "entity_id":79279,
        "entity_label":"<https:\/\/www.wikidata.org\/wiki\/Q5507945>",
        "still_valid":false,
        "origin":"q(?w) :- P22(?_,?x)^P25(?_,?x)^P40(?x,?w)",
        "score_calibrated":0.0000040757,
        "score_combined":0.0000000512,
        "local_kg_hit_rewriting":false,
        "online_kg_hit_rewriting":false,
        "local_kg_hit_original":false,
        "online_kg_hit_original":false
    },
    "45":{
        "entity_id":91884,
        "entity_label":"<https:\/\/www.wikidata.org\/wiki\/Q657636>",
        "still_valid":false,
        "origin":"q(?w) :- P22(?_,?x)^P25(?_,?x)^P40(?x,?w)",
        "score_calibrated":0.0000039896,
        "score_combined":0.0000000501,
        "local_kg_hit_rewriting":false,
        "online_kg_hit_rewriting":false,
        "local_kg_hit_original":false,
        "online_kg_hit_original":false
    },
    "46":{
        "entity_id":88982,
        "entity_label":"<https:\/\/www.wikidata.org\/wiki\/Q62885>",
        "still_valid":false,
        "origin":"q(?w) :- P22(?_,?x)^P25(?_,?x)^P40(?x,?w)",
        "score_calibrated":0.0000039607,
        "score_combined":0.0000000497,
        "local_kg_hit_rewriting":false,
        "online_kg_hit_rewriting":false,
        "local_kg_hit_original":false,
        "online_kg_hit_original":false
    },
    "47":{
        "entity_id":28367,
        "entity_label":"<https:\/\/www.wikidata.org\/wiki\/Q2149473>",
        "still_valid":false,
        "origin":"q(?w) :- P22(?_,?x)^P25(?_,?x)^P40(?x,?w)",
        "score_calibrated":0.0000039291,
        "score_combined":0.0000000493,
        "local_kg_hit_rewriting":false,
        "online_kg_hit_rewriting":false,
        "local_kg_hit_original":false,
        "online_kg_hit_original":false
    },
    "48":{
        "entity_id":97584,
        "entity_label":"<https:\/\/www.wikidata.org\/wiki\/Q70930>",
        "still_valid":false,
        "origin":"q(?w) :- P22(?_,?x)^P25(?_,?x)^P40(?x,?w)",
        "score_calibrated":0.0000039091,
        "score_combined":0.0000000491,
        "local_kg_hit_rewriting":false,
        "online_kg_hit_rewriting":false,
        "local_kg_hit_original":false,
        "online_kg_hit_original":false
    },
    "49":{
        "entity_id":32629,
        "entity_label":"<https:\/\/www.wikidata.org\/wiki\/Q237886>",
        "still_valid":false,
        "origin":"q(?w) :- P22(?_,?x)^P25(?_,?x)^P40(?x,?w)",
        "score_calibrated":0.0000037146,
        "score_combined":0.0000000466,
        "local_kg_hit_rewriting":false,
        "online_kg_hit_rewriting":false,
        "local_kg_hit_original":false,
        "online_kg_hit_original":false
    },
    "50":{
        "entity_id":112894,
        "entity_label":"<https:\/\/www.wikidata.org\/wiki\/Q905425>",
        "still_valid":false,
        "origin":"q(?w) :- P22(?_,?x)^P25(?_,?x)^P40(?x,?w)",
        "score_calibrated":0.0000031712,
        "score_combined":0.0000000398,
        "local_kg_hit_rewriting":false,
        "online_kg_hit_rewriting":false,
        "local_kg_hit_original":false,
        "online_kg_hit_original":false
    },
    "51":{
        "entity_id":40462,
        "entity_label":"<https:\/\/www.wikidata.org\/wiki\/Q282516>",
        "still_valid":false,
        "origin":"q(?w) :- P22(?_,?x)^P25(?_,?x)^P40(?x,?w)",
        "score_calibrated":0.0000030838,
        "score_combined":0.0000000387,
        "local_kg_hit_rewriting":false,
        "online_kg_hit_rewriting":false,
        "local_kg_hit_original":false,
        "online_kg_hit_original":false
    },
    "52":{
        "entity_id":29516,
        "entity_label":"<https:\/\/www.wikidata.org\/wiki\/Q220994>",
        "still_valid":false,
        "origin":"q(?w) :- P22(?_,?x)^P25(?_,?x)^P40(?x,?w)",
        "score_calibrated":0.0000030768,
        "score_combined":0.0000000386,
        "local_kg_hit_rewriting":false,
        "online_kg_hit_rewriting":false,
        "local_kg_hit_original":false,
        "online_kg_hit_original":false
    },
    "53":{
        "entity_id":30391,
        "entity_label":"<https:\/\/www.wikidata.org\/wiki\/Q2293930>",
        "still_valid":false,
        "origin":"q(?w) :- P22(?_,?x)^P25(?_,?x)^P40(?x,?w)",
        "score_calibrated":0.0000030277,
        "score_combined":0.000000038,
        "local_kg_hit_rewriting":false,
        "online_kg_hit_rewriting":false,
        "local_kg_hit_original":false,
        "online_kg_hit_original":false
    },
    "54":{
        "entity_id":51893,
        "entity_label":"<https:\/\/www.wikidata.org\/wiki\/Q3436301>",
        "still_valid":false,
        "origin":"q(?w) :- P22(?_,?x)^P25(?_,?x)^P40(?x,?w)",
        "score_calibrated":0.000002934,
        "score_combined":0.0000000368,
        "local_kg_hit_rewriting":false,
        "online_kg_hit_rewriting":false,
        "local_kg_hit_original":false,
        "online_kg_hit_original":false
    },
    "55":{
        "entity_id":17669,
        "entity_label":"<https:\/\/www.wikidata.org\/wiki\/Q16863346>",
        "still_valid":false,
        "origin":"q(?w) :- P22(?_,?x)^P25(?_,?x)^P40(?x,?w)",
        "score_calibrated":0.0000028924,
        "score_combined":0.0000000363,
        "local_kg_hit_rewriting":false,
        "online_kg_hit_rewriting":false,
        "local_kg_hit_original":false,
        "online_kg_hit_original":false
    },
    "56":{
        "entity_id":191,
        "entity_label":"<https:\/\/www.wikidata.org\/wiki\/Q102005>",
        "still_valid":false,
        "origin":"q(?w) :- P22(?_,?x)^P25(?_,?x)^P40(?x,?w)",
        "score_calibrated":0.0000028636,
        "score_combined":0.0000000359,
        "local_kg_hit_rewriting":false,
        "online_kg_hit_rewriting":false,
        "local_kg_hit_original":false,
        "online_kg_hit_original":false
    },
    "57":{
        "entity_id":104839,
        "entity_label":"<https:\/\/www.wikidata.org\/wiki\/Q7548189>",
        "still_valid":false,
        "origin":"q(?w) :- P22(?_,?x)^P25(?_,?x)^P40(?x,?w)",
        "score_calibrated":0.0000028375,
        "score_combined":0.0000000356,
        "local_kg_hit_rewriting":false,
        "online_kg_hit_rewriting":false,
        "local_kg_hit_original":false,
        "online_kg_hit_original":false
    },
    "58":{
        "entity_id":57819,
        "entity_label":"<https:\/\/www.wikidata.org\/wiki\/Q391944>",
        "still_valid":false,
        "origin":"q(?w) :- P22(?_,?x)^P25(?_,?x)^P40(?x,?w)",
        "score_calibrated":0.00000278,
        "score_combined":0.0000000349,
        "local_kg_hit_rewriting":false,
        "online_kg_hit_rewriting":false,
        "local_kg_hit_original":false,
        "online_kg_hit_original":false
    },
    "59":{
        "entity_id":69957,
        "entity_label":"<https:\/\/www.wikidata.org\/wiki\/Q4948190>",
        "still_valid":false,
        "origin":"q(?w) :- P22(?_,?x)^P25(?_,?x)^P40(?x,?w)",
        "score_calibrated":0.0000027104,
        "score_combined":0.000000034,
        "local_kg_hit_rewriting":false,
        "online_kg_hit_rewriting":false,
        "local_kg_hit_original":false,
        "online_kg_hit_original":false
    },
    "60":{
        "entity_id":63881,
        "entity_label":"<https:\/\/www.wikidata.org\/wiki\/Q459159>",
        "still_valid":false,
        "origin":"q(?w) :- P22(?_,?x)^P25(?_,?x)^P40(?x,?w)",
        "score_calibrated":0.0000026371,
        "score_combined":0.0000000331,
        "local_kg_hit_rewriting":false,
        "online_kg_hit_rewriting":false,
        "local_kg_hit_original":false,
        "online_kg_hit_original":false
    },
    "61":{
        "entity_id":108948,
        "entity_label":"<https:\/\/www.wikidata.org\/wiki\/Q79759>",
        "still_valid":false,
        "origin":"q(?w) :- P22(?_,?x)^P25(?_,?x)^P40(?x,?w)",
        "score_calibrated":0.0000025236,
        "score_combined":0.0000000317,
        "local_kg_hit_rewriting":false,
        "online_kg_hit_rewriting":false,
        "local_kg_hit_original":false,
        "online_kg_hit_original":false
    },
    "62":{
        "entity_id":72784,
        "entity_label":"<https:\/\/www.wikidata.org\/wiki\/Q5121114>",
        "still_valid":false,
        "origin":"q(?w) :- P22(?_,?x)^P25(?_,?x)^P40(?x,?w)",
        "score_calibrated":0.000002495,
        "score_combined":0.0000000313,
        "local_kg_hit_rewriting":false,
        "online_kg_hit_rewriting":false,
        "local_kg_hit_original":false,
        "online_kg_hit_original":false
    },
    "63":{
        "entity_id":57392,
        "entity_label":"<https:\/\/www.wikidata.org\/wiki\/Q3852378>",
        "still_valid":false,
        "origin":"q(?w) :- P22(?_,?x)^P25(?_,?x)^P40(?x,?w)",
        "score_calibrated":0.0000023855,
        "score_combined":0.0000000299,
        "local_kg_hit_rewriting":false,
        "online_kg_hit_rewriting":false,
        "local_kg_hit_original":false,
        "online_kg_hit_original":false
    },
    "64":{
        "entity_id":97354,
        "entity_label":"<https:\/\/www.wikidata.org\/wiki\/Q708265>",
        "still_valid":false,
        "origin":"q(?w) :- P22(?_,?x)^P25(?_,?x)^P40(?x,?w)",
        "score_calibrated":0.0000023847,
        "score_combined":0.0000000299,
        "local_kg_hit_rewriting":false,
        "online_kg_hit_rewriting":false,
        "local_kg_hit_original":false,
        "online_kg_hit_original":false
    },
    "65":{
        "entity_id":92591,
        "entity_label":"<https:\/\/www.wikidata.org\/wiki\/Q6681668>",
        "still_valid":false,
        "origin":"q(?w) :- P22(?_,?x)^P25(?_,?x)^P40(?x,?w)",
        "score_calibrated":0.0000023392,
        "score_combined":0.0000000294,
        "local_kg_hit_rewriting":false,
        "online_kg_hit_rewriting":false,
        "local_kg_hit_original":false,
        "online_kg_hit_original":false
    },
    "66":{
        "entity_id":102217,
        "entity_label":"<https:\/\/www.wikidata.org\/wiki\/Q735512>",
        "still_valid":false,
        "origin":"q(?w) :- P22(?_,?x)^P25(?_,?x)^P40(?x,?w)",
        "score_calibrated":0.0000023027,
        "score_combined":0.0000000289,
        "local_kg_hit_rewriting":false,
        "online_kg_hit_rewriting":false,
        "local_kg_hit_original":false,
        "online_kg_hit_original":false
    },
    "67":{
        "entity_id":45867,
        "entity_label":"<https:\/\/www.wikidata.org\/wiki\/Q313042>",
        "still_valid":false,
        "origin":"q(?w) :- P22(?_,?x)^P25(?_,?x)^P40(?x,?w)",
        "score_calibrated":0.0000021798,
        "score_combined":0.0000000274,
        "local_kg_hit_rewriting":false,
        "online_kg_hit_rewriting":false,
        "local_kg_hit_original":false,
        "online_kg_hit_original":false
    },
    "68":{
        "entity_id":110416,
        "entity_label":"<https:\/\/www.wikidata.org\/wiki\/Q81212>",
        "still_valid":false,
        "origin":"q(?w) :- P22(?_,?x)^P25(?_,?x)^P40(?x,?w)",
        "score_calibrated":0.0000021193,
        "score_combined":0.0000000266,
        "local_kg_hit_rewriting":false,
        "online_kg_hit_rewriting":false,
        "local_kg_hit_original":false,
        "online_kg_hit_original":false
    },
    "69":{
        "entity_id":3612,
        "entity_label":"<https:\/\/www.wikidata.org\/wiki\/Q1159234>",
        "still_valid":false,
        "origin":"q(?w) :- P22(?_,?x)^P25(?_,?x)^P40(?x,?w)",
        "score_calibrated":0.0000021126,
        "score_combined":0.0000000265,
        "local_kg_hit_rewriting":false,
        "online_kg_hit_rewriting":false,
        "local_kg_hit_original":false,
        "online_kg_hit_original":false
    },
    "70":{
        "entity_id":16847,
        "entity_label":"<https:\/\/www.wikidata.org\/wiki\/Q167317>",
        "still_valid":false,
        "origin":"q(?w) :- P22(?_,?x)^P25(?_,?x)^P40(?x,?w)",
        "score_calibrated":0.0000020967,
        "score_combined":0.0000000263,
        "local_kg_hit_rewriting":false,
        "online_kg_hit_rewriting":false,
        "local_kg_hit_original":false,
        "online_kg_hit_original":false
    },
    "71":{
        "entity_id":89344,
        "entity_label":"<https:\/\/www.wikidata.org\/wiki\/Q6313730>",
        "still_valid":false,
        "origin":"q(?w) :- P22(?_,?x)^P25(?_,?x)^P40(?x,?w)",
        "score_calibrated":0.0000020925,
        "score_combined":0.0000000263,
        "local_kg_hit_rewriting":false,
        "online_kg_hit_rewriting":false,
        "local_kg_hit_original":false,
        "online_kg_hit_original":false
    },
    "72":{
        "entity_id":32568,
        "entity_label":"<https:\/\/www.wikidata.org\/wiki\/Q23770316>",
        "still_valid":false,
        "origin":"q(?w) :- P22(?_,?x)^P25(?_,?x)^P40(?x,?w)",
        "score_calibrated":0.0000020477,
        "score_combined":0.0000000257,
        "local_kg_hit_rewriting":false,
        "online_kg_hit_rewriting":false,
        "local_kg_hit_original":false,
        "online_kg_hit_original":false
    },
    "73":{
        "entity_id":64740,
        "entity_label":"<https:\/\/www.wikidata.org\/wiki\/Q466287>",
        "still_valid":false,
        "origin":"q(?w) :- P22(?_,?x)^P25(?_,?x)^P40(?x,?w)",
        "score_calibrated":0.0000020111,
        "score_combined":0.0000000252,
        "local_kg_hit_rewriting":false,
        "online_kg_hit_rewriting":false,
        "local_kg_hit_original":false,
        "online_kg_hit_original":false
    },
    "74":{
        "entity_id":4072,
        "entity_label":"<https:\/\/www.wikidata.org\/wiki\/Q11779320>",
        "still_valid":false,
        "origin":"q(?w) :- P22(?_,?x)^P25(?_,?x)^P40(?x,?w)",
        "score_calibrated":0.0000020013,
        "score_combined":0.0000000251,
        "local_kg_hit_rewriting":false,
        "online_kg_hit_rewriting":false,
        "local_kg_hit_original":false,
        "online_kg_hit_original":false
    },
    "75":{
        "entity_id":47631,
        "entity_label":"<https:\/\/www.wikidata.org\/wiki\/Q3189144>",
        "still_valid":false,
        "origin":"q(?w) :- P22(?_,?x)^P25(?_,?x)^P40(?x,?w)",
        "score_calibrated":0.0000019884,
        "score_combined":0.000000025,
        "local_kg_hit_rewriting":false,
        "online_kg_hit_rewriting":false,
        "local_kg_hit_original":false,
        "online_kg_hit_original":false
    },
    "76":{
        "entity_id":56198,
        "entity_label":"<https:\/\/www.wikidata.org\/wiki\/Q37594>",
        "still_valid":false,
        "origin":"q(?w) :- P22(?_,?x)^P25(?_,?x)^P40(?x,?w)",
        "score_calibrated":0.0000019805,
        "score_combined":0.0000000249,
        "local_kg_hit_rewriting":false,
        "online_kg_hit_rewriting":false,
        "local_kg_hit_original":false,
        "online_kg_hit_original":false
    },
    "77":{
        "entity_id":105092,
        "entity_label":"<https:\/\/www.wikidata.org\/wiki\/Q7595808>",
        "still_valid":false,
        "origin":"q(?w) :- P22(?_,?x)^P25(?_,?x)^P40(?x,?w)",
        "score_calibrated":0.0000019789,
        "score_combined":0.0000000248,
        "local_kg_hit_rewriting":false,
        "online_kg_hit_rewriting":false,
        "local_kg_hit_original":false,
        "online_kg_hit_original":false
    },
    "78":{
        "entity_id":11193,
        "entity_label":"<https:\/\/www.wikidata.org\/wiki\/Q150872>",
        "still_valid":false,
        "origin":"q(?w) :- P22(?_,?x)^P25(?_,?x)^P40(?x,?w)",
        "score_calibrated":0.0000019544,
        "score_combined":0.0000000245,
        "local_kg_hit_rewriting":false,
        "online_kg_hit_rewriting":false,
        "local_kg_hit_original":false,
        "online_kg_hit_original":false
    },
    "79":{
        "entity_id":82600,
        "entity_label":"<https:\/\/www.wikidata.org\/wiki\/Q571957>",
        "still_valid":false,
        "origin":"q(?w) :- P22(?_,?x)^P25(?_,?x)^P40(?x,?w)",
        "score_calibrated":0.0000019428,
        "score_combined":0.0000000244,
        "local_kg_hit_rewriting":false,
        "online_kg_hit_rewriting":false,
        "local_kg_hit_original":false,
        "online_kg_hit_original":false
    },
    "80":{
        "entity_id":107737,
        "entity_label":"<https:\/\/www.wikidata.org\/wiki\/Q7828080>",
        "still_valid":false,
        "origin":"q(?w) :- P22(?_,?x)^P25(?_,?x)^P40(?x,?w)",
        "score_calibrated":0.0000019253,
        "score_combined":0.0000000242,
        "local_kg_hit_rewriting":false,
        "online_kg_hit_rewriting":false,
        "local_kg_hit_original":false,
        "online_kg_hit_original":false
    },
    "81":{
        "entity_id":109525,
        "entity_label":"<https:\/\/www.wikidata.org\/wiki\/Q8014387>",
        "still_valid":false,
        "origin":"q(?w) :- P22(?_,?x)^P25(?_,?x)^P40(?x,?w)",
        "score_calibrated":0.0000018964,
        "score_combined":0.0000000238,
        "local_kg_hit_rewriting":false,
        "online_kg_hit_rewriting":false,
        "local_kg_hit_original":false,
        "online_kg_hit_original":false
    },
    "82":{
        "entity_id":90947,
        "entity_label":"<https:\/\/www.wikidata.org\/wiki\/Q647954>",
        "still_valid":false,
        "origin":"q(?w) :- P22(?_,?x)^P25(?_,?x)^P40(?x,?w)",
        "score_calibrated":0.0000018928,
        "score_combined":0.0000000238,
        "local_kg_hit_rewriting":false,
        "online_kg_hit_rewriting":false,
        "local_kg_hit_original":false,
        "online_kg_hit_original":false
    },
    "83":{
        "entity_id":37951,
        "entity_label":"<https:\/\/www.wikidata.org\/wiki\/Q2683307>",
        "still_valid":false,
        "origin":"q(?w) :- P22(?_,?x)^P25(?_,?x)^P40(?x,?w)",
        "score_calibrated":0.0000018671,
        "score_combined":0.0000000234,
        "local_kg_hit_rewriting":false,
        "online_kg_hit_rewriting":false,
        "local_kg_hit_original":false,
        "online_kg_hit_original":false
    },
    "84":{
        "entity_id":13822,
        "entity_label":"<https:\/\/www.wikidata.org\/wiki\/Q160115>",
        "still_valid":false,
        "origin":"q(?w) :- P22(?_,?x)^P25(?_,?x)^P40(?x,?w)",
        "score_calibrated":0.0000018571,
        "score_combined":0.0000000233,
        "local_kg_hit_rewriting":false,
        "online_kg_hit_rewriting":false,
        "local_kg_hit_original":false,
        "online_kg_hit_original":false
    },
    "85":{
        "entity_id":111047,
        "entity_label":"<https:\/\/www.wikidata.org\/wiki\/Q840422>",
        "still_valid":false,
        "origin":"q(?w) :- P22(?_,?x)^P25(?_,?x)^P40(?x,?w)",
        "score_calibrated":0.0000017795,
        "score_combined":0.0000000223,
        "local_kg_hit_rewriting":false,
        "online_kg_hit_rewriting":false,
        "local_kg_hit_original":false,
        "online_kg_hit_original":false
    },
    "86":{
        "entity_id":3010,
        "entity_label":"<https:\/\/www.wikidata.org\/wiki\/Q113570>",
        "still_valid":false,
        "origin":"q(?w) :- P22(?_,?x)^P25(?_,?x)^P40(?x,?w)",
        "score_calibrated":0.0000017442,
        "score_combined":0.0000000219,
        "local_kg_hit_rewriting":false,
        "online_kg_hit_rewriting":false,
        "local_kg_hit_original":false,
        "online_kg_hit_original":false
    },
    "87":{
        "entity_id":67959,
        "entity_label":"<https:\/\/www.wikidata.org\/wiki\/Q4799410>",
        "still_valid":false,
        "origin":"q(?w) :- P22(?_,?x)^P25(?_,?x)^P40(?x,?w)",
        "score_calibrated":0.0000017438,
        "score_combined":0.0000000219,
        "local_kg_hit_rewriting":false,
        "online_kg_hit_rewriting":false,
        "local_kg_hit_original":false,
        "online_kg_hit_original":false
    },
    "88":{
        "entity_id":57423,
        "entity_label":"<https:\/\/www.wikidata.org\/wiki\/Q3856501>",
        "still_valid":false,
        "origin":"q(?w) :- P22(?_,?x)^P25(?_,?x)^P40(?x,?w)",
        "score_calibrated":0.0000017391,
        "score_combined":0.0000000218,
        "local_kg_hit_rewriting":false,
        "online_kg_hit_rewriting":false,
        "local_kg_hit_original":false,
        "online_kg_hit_original":false
    },
    "89":{
        "entity_id":61,
        "entity_label":"<https:\/\/www.wikidata.org\/wiki\/Q10066>",
        "still_valid":false,
        "origin":"q(?w) :- P22(?_,?x)^P25(?_,?x)^P40(?x,?w)",
        "score_calibrated":0.0000017282,
        "score_combined":0.0000000217,
        "local_kg_hit_rewriting":false,
        "online_kg_hit_rewriting":false,
        "local_kg_hit_original":false,
        "online_kg_hit_original":false
    },
    "90":{
        "entity_id":23214,
        "entity_label":"<https:\/\/www.wikidata.org\/wiki\/Q1910368>",
        "still_valid":false,
        "origin":"q(?w) :- P22(?_,?x)^P25(?_,?x)^P40(?x,?w)",
        "score_calibrated":0.0000017122,
        "score_combined":0.0000000215,
        "local_kg_hit_rewriting":false,
        "online_kg_hit_rewriting":false,
        "local_kg_hit_original":false,
        "online_kg_hit_original":false
    },
    "91":{
        "entity_id":92353,
        "entity_label":"<https:\/\/www.wikidata.org\/wiki\/Q66645>",
        "still_valid":false,
        "origin":"q(?w) :- P22(?_,?x)^P25(?_,?x)^P40(?x,?w)",
        "score_calibrated":0.0000017107,
        "score_combined":0.0000000215,
        "local_kg_hit_rewriting":false,
        "online_kg_hit_rewriting":false,
        "local_kg_hit_original":false,
        "online_kg_hit_original":false
    },
    "92":{
        "entity_id":32271,
        "entity_label":"<https:\/\/www.wikidata.org\/wiki\/Q236554>",
        "still_valid":false,
        "origin":"q(?w) :- P22(?_,?x)^P25(?_,?x)^P40(?x,?w)",
        "score_calibrated":0.0000016803,
        "score_combined":0.0000000211,
        "local_kg_hit_rewriting":false,
        "online_kg_hit_rewriting":false,
        "local_kg_hit_original":false,
        "online_kg_hit_original":false
    },
    "93":{
        "entity_id":63978,
        "entity_label":"<https:\/\/www.wikidata.org\/wiki\/Q459947>",
        "still_valid":false,
        "origin":"q(?w) :- P22(?_,?x)^P25(?_,?x)^P40(?x,?w)",
        "score_calibrated":0.0000016773,
        "score_combined":0.0000000211,
        "local_kg_hit_rewriting":false,
        "online_kg_hit_rewriting":false,
        "local_kg_hit_original":false,
        "online_kg_hit_original":false
    },
    "94":{
        "entity_id":83957,
        "entity_label":"<https:\/\/www.wikidata.org\/wiki\/Q588407>",
        "still_valid":false,
        "origin":"q(?w) :- P22(?_,?x)^P25(?_,?x)^P40(?x,?w)",
        "score_calibrated":0.0000016538,
        "score_combined":0.0000000208,
        "local_kg_hit_rewriting":false,
        "online_kg_hit_rewriting":false,
        "local_kg_hit_original":false,
        "online_kg_hit_original":false
    },
    "95":{
        "entity_id":97287,
        "entity_label":"<https:\/\/www.wikidata.org\/wiki\/Q7077885>",
        "still_valid":false,
        "origin":"q(?w) :- P22(?_,?x)^P25(?_,?x)^P40(?x,?w)",
        "score_calibrated":0.0000016534,
        "score_combined":0.0000000208,
        "local_kg_hit_rewriting":false,
        "online_kg_hit_rewriting":false,
        "local_kg_hit_original":false,
        "online_kg_hit_original":false
    },
    "96":{
        "entity_id":47161,
        "entity_label":"<https:\/\/www.wikidata.org\/wiki\/Q3177046>",
        "still_valid":false,
        "origin":"q(?w) :- P22(?_,?x)^P25(?_,?x)^P40(?x,?w)",
        "score_calibrated":0.000001646,
        "score_combined":0.0000000207,
        "local_kg_hit_rewriting":false,
        "online_kg_hit_rewriting":false,
        "local_kg_hit_original":false,
        "online_kg_hit_original":false
    },
    "97":{
        "entity_id":46100,
        "entity_label":"<https:\/\/www.wikidata.org\/wiki\/Q313482>",
        "still_valid":false,
        "origin":"q(?w) :- P22(?_,?x)^P25(?_,?x)^P40(?x,?w)",
        "score_calibrated":0.0000016413,
        "score_combined":0.0000000206,
        "local_kg_hit_rewriting":false,
        "online_kg_hit_rewriting":false,
        "local_kg_hit_original":false,
        "online_kg_hit_original":false
    },
    "98":{
        "entity_id":66404,
        "entity_label":"<https:\/\/www.wikidata.org\/wiki\/Q4725860>",
        "still_valid":false,
        "origin":"q(?w) :- P22(?_,?x)^P25(?_,?x)^P40(?x,?w)",
        "score_calibrated":0.0000016302,
        "score_combined":0.0000000205,
        "local_kg_hit_rewriting":false,
        "online_kg_hit_rewriting":false,
        "local_kg_hit_original":false,
        "online_kg_hit_original":false
    },
    "99":{
        "entity_id":13720,
        "entity_label":"<https:\/\/www.wikidata.org\/wiki\/Q16006358>",
        "still_valid":false,
        "origin":"q(?w) :- P22(?_,?x)^P25(?_,?x)^P40(?x,?w)",
        "score_calibrated":0.0000016228,
        "score_combined":0.0000000204,
        "local_kg_hit_rewriting":false,
        "online_kg_hit_rewriting":false,
        "local_kg_hit_original":false,
        "online_kg_hit_original":false
    }
}